Workbook

Sheet LEIA-ME
A1: PPR Comex · Planilha de controle
A3: Colunas azuis: você (ou o agente) preenche. Colunas verdes: fórmulas, não editar.
A4: Comece pela aba Parametros: troque o Mês de referência todo mês (sempre dia 01).
A6: Meta 1 · Volume (75 t/mês): aba Pedidos (só lançar pedidos; o Painel calcula).
A7: Meta 2 · Positivação +20%: abas Clientes, Pedidos e Acompanhamento.
A8: Clientes: um por linha, com a periodicidade de compra (1, 2, 3, 4, 6 ou 12 meses).
A9: Pedidos: lançar os pedidos do ano base (2025) e do ano meta (2026).
A10: Acompanhamento: um registro por cliente que não recomprou no mês, com motivo e ação.
A11: Meta 3a · Gestão das S.A.: aba S_Atividades (uma linha por atividade solicitada).
A12: O prazo de cada setor vem da tabela de SLA da aba Parametros se a coluna Prazo ficar vazia.
A13: Registre cada cobrança feita (Nº cobranças e Última cobrança): é a prova da sua gestão.
A14: Meta 3b · Redução de custo: aba Custos (uma linha por ação; referência x realizado).
... A17: Relatório do mês: python3 ppr-comex/scripts/relatorio_mensal.py <planilha> --mes AAAA-MM

Sheet Painel
A1: Painel PPR Comex · mês de referência: | B1: =Parametros!$B$2
A2: META 1 · VOLUME
A3: Toneladas vendidas no mês | B3: =SUMIFS(Pedidos!$E:$E,Pedidos!$B:$B,">="&Parametros!$B$2,Pedidos!$B:$B,"<="&EOMONTH(Parametros!$B$2,0))
A4: Média mensal no ano (até o mês de referência) | B4: =SUMIFS(Pedidos!$E:$E,Pedidos!$K:$K,Parametros!$B$4,Pedidos!$B:$B,"<="&EOMONTH(Parametros!$B$2,0))/MONTH(Parametros!$B$2)
A5: Meta (t/mês) | B5: =Parametros!$B$6
A6: META 2 · POSITIVAÇÃO
A7: Clientes positivados no ano base | B7: =COUNTIF(Clientes!$I:$I,">0")
A8: Meta de clientes no ano (+20%) | B8: =ROUNDUP(B7*(1+Parametros!$B$5),0)
A9: Clientes positivados no ano meta (acumulado) | B9: =COUNTIF(Clientes!$K:$K,">0")
A10: Pedidos no ano base | B10: =COUNTIF(Pedidos!$K:$K,Parametros!$B$3)
A11: Meta de pedidos no ano (+20%) | B11: =ROUNDUP(B10*(1+Parametros!$B$5),0)
A12: Pedidos no ano meta (acumulado) | B12: =COUNTIF(Pedidos!$K:$K,Parametros!$B$4)
A13: Clientes que compraram no mês | B13: =COUNTIF(Clientes!$N:$N,"Comprou no mês")
A14: Clientes previstos no mês e ainda sem pedido | B14: =COUNTIF(Clientes!$N:$N,"Previsto no mês")
A15: Clientes atrasados na recompra | B15: =COUNTIF(Clientes!$N:$N,"Atrasado")
A16: Motivos registrados no mês | B16: =COUNTIFS(Acompanhamento!$A:$A,Parametros!$B$2)
A17: META 3a · S.A. E PRAZO DE EMBARQUE
A18: Atividades concluídas no mês | B18: =COUNTIFS(S_Atividades!$G:$G,">="&Parametros!$B$2,S_Atividades!$G:$G,"<="&EOMONTH(Parametros!$B$2,0))
A19: % concluídas no prazo | B19: =IFERROR(COUNTIFS(S_Atividades!$G:$G,">="&Parametros!$B$2,S_Atividades!$G:$G,"<="&EOMONTH(Parametros!$B$2,0),S_Atividades!$M:$M,"No prazo")/B18,"")
A20: Atividades em aberto atrasadas (hoje) | B20: =COUNTIF(S_Atividades!$M:$M,"Atrasada")
A21: Cobranças feitas (atividades do mês) | B21: =SUMIFS(S_Atividades!$H:$H,S_Atividades!$E:$E,">="&Parametros!$B$2,S_Atividades!$E:$E,"<="&EOMONTH(Parametros!$B$2,0))
A22: Pedidos embarcados no mês | B22: =COUNTIFS(Pedidos!$I:$I,">="&Parametros!$B$2,Pedidos!$I:$I,"<="&EOMONTH(Parametros!$B$2,0))
A23: % embarcados no prazo negociado | B23: =IFERROR(COUNTIFS(Pedidos!$I:$I,">="&Parametros!$B$2,Pedidos!$I:$I,"<="&EOMONTH(Parametros!$B$2,0),Pedidos!$N:$N,"No prazo")/B22,"")
A24: META 3b · REDUÇÃO DE CUSTO
A25: Economia registrada no mês (R$) | B25: =SUMIFS(Custos!$I:$I,Custos!$A:$A,Parametros!$B$2)
A26: Economia acumulada no ano (R$) | B26: =SUMIFS(Custos!$I:$I,Custos!$A:$A,">="&DATE(Parametros!$B$4,1,1),Custos!$A:$A,"<="&EOMONTH(Parametros!$B$2,0))
A27: META 3c · GIRO DE EMBALAGENS
A28: Valor parado em embalagens obsoletas (R$) | B28: =SUMIFS(Embalagens!$O:$O,Embalagens!$L:$L,"Obsoleta")
A29: Valor reaproveitado no mês (R$) | B29: =SUMIFS(Uso_Embalagens!$J:$J,Uso_Embalagens!$A:$A,">="&Parametros!$B$2,Uso_Embalagens!$A:$A,"<="&EOMONTH(Parametros!$B$2,0))
A30: Unidades reaproveitadas no mês | B30: =SUMIFS(Uso_Embalagens!$E:$E,Uso_Embalagens!$A:$A,">="&Parametros!$B$2,Uso_Embalagens!$A:$A,"<="&EOMONTH(Parametros!$B$2,0))

Sheet Parametros
A1: Parâmetro | B1: Valor | C1: Observação | E1: Departamento | F1: Prazo padrão (dias)
A2: Mês de referência | B2: 46266 | C2: Primeiro dia do mês que está sendo apurado | E2: Comercial/Comex | F2: 2
A3: Ano base | B3: 2025 | C3: Ano usado como base da positivação | E3: Compras/Suprimentos | F3: 10
A4: Ano meta | B4: 2026 | C4: Ano do PPR | E4: Marketing/Arte | F4: 7
A5: Meta de aumento de positivação | B5: 0.2 | C5: 20% sobre o ano base | E5: Qualidade/Regulatório | F5: 7
A6: Meta de volume (t/mês) | B6: 75 | C6: Média mensal | E6: PCP/Produção | F6: 15
A7: Prazo de embarque padrão (dias) | B7: 30 | C7: Prazo negociado com o cliente | E7: Logística/Embarque | F7: 5
A8: Idade para obsoleta (meses) | B8: 12 | C8: Embalagem parada há mais tempo que isso | E8: Financeiro | F8: 3
E9: Documentação/Despachante | F9: 5

Sheet Clientes
A1: Cód. Cliente | B1: Cliente | C1: País | D1: Idioma | E1: Canal/Representante | F1: Periodicidade (meses) | G1: Status cadastro | H1: Observação | I1: Pedidos ano base | J1: Toneladas ano base | K1: Pedidos ano meta | L1: Último pedido | M1: Próxima compra prevista | N1: Situação no mês
A2: C001 | B2: Cliente Exemplo 01 | C2: Estados Unidos | D2: Inglês | E2: Agente LatAm | F2: 2 | G2: Ativo | I2: =IF(A2="","",COUNTIFS(Pedidos!$C:$C,A2,Pedidos!$K:$K,Parametros!$B$3)) | J2: =IF(A2="","",SUMIFS(Pedidos!$E:$E,Pedidos!$C:$C,A2,Pedidos!$K:$K,Parametros!$B$3)) | K2: =IF(A2="","",COUNTIFS(Pedidos!$C:$C,A2,Pedidos!$K:$K,Parametros!$B$4)) | L2: =IF(A2="","",IF(COUNTIFS(Pedidos!$C:$C,A2,Pedidos!$B:$B,"<="&EOMONTH(Parametros!$B$2,0))=0,"",_xlfn.MAXIFS(Pedidos!$B:$B,Pedidos!$C:$C,A2,Pedidos!$B:$B,"<="&EOMONTH(Parametros!$B$2,0)))) | M2: =IF(OR(L2="",F2=""),"",EDATE(L2,F2)) | N2: =IF(A2="","",IF(L2="","Sem histórico",IF(AND(L2>=Parametros!$B$2,L2<=EOMONTH(Parametros!$B$2,0)),"Comprou no mês",IF(M2="","Sem periodicidade",IF(M2<Parametros!$B$2,"Atrasado",IF(M2<=EOMONTH(Parametros!$B$2,0),"Previsto no mês","Em dia"))))))
A3: C002 | B3: Cliente Exemplo 02 | C3: Paraguai | D3: Espanhol | E3: Trading | F3: 1 | G3: Ativo | I3: =IF(A3="","",COUNTIFS(Pedidos!$C:$C,A3,Pedidos!$K:$K,Parametros!$B$3)) | J3: =IF(A3="","",SUMIFS(Pedidos!$E:$E,Pedidos!$C:$C,A3,Pedidos!$K:$K,Parametros!$B$3)) | K3: =IF(A3="","",COUNTIFS(Pedidos!$C:$C,A3,Pedidos!$K:$K,Parametros!$B$4)) | L3: =IF(A3="","",IF(COUNTIFS(Pedidos!$C:$C,A3,Pedidos!$B:$B,"<="&EOMONTH(Parametros!$B$2,0))=0,"",_xlfn.MAXIFS(Pedidos!$B:$B,Pedidos!$C:$C,A3,Pedidos!$B:$B,"<="&EOMONTH(Parametros!$B$2,0)))) | M3: =IF(OR(L3="",F3=""),"",EDATE(L3,F3)) | N3: =IF(A3="","",IF(L3="","Sem histórico",IF(AND(L3>=Parametros!$B$2,L3<=EOMONTH(Parametros!$B$2,0)),"Comprou no mês",IF(M3="","Sem periodicidade",IF(M3<Parametros!$B$2,"Atrasado",IF(M3<=EOMONTH(Parametros!$B$2,0),"Previsto no mês","Em dia"))))))
A4: C003 | B4: Cliente Exemplo 03 | C4: Chile | D4: Espanhol | E4: Trading | F4: 2 | G4: Ativo | I4: =IF(A4="","",COUNTIFS(Pedidos!$C:$C,A4,Pedidos!$K:$K,Parametros!$B$3)) | J4: =IF(A4="","",SUMIFS(Pedidos!$E:$E,Pedidos!$C:$C,A4,Pedidos!$K:$K,Parametros!$B$3)) | K4: =IF(A4="","",COUNTIFS(Pedidos!$C:$C,A4,Pedidos!$K:$K,Parametros!$B$4)) | L4: =IF(A4="","",IF(COUNTIFS(Pedidos!$C:$C,A4,Pedidos!$B:$B,"<="&EOMONTH(Parametros!$B$2,0))=0,"",_xlfn.MAXIFS(Pedidos!$B:$B,Pedidos!$C:$C,A4,Pedidos!$B:$B,"<="&EOMONTH(Parametros!$B$2,0)))) | M4: =IF(OR(L4="",F4=""),"",EDATE(L4,F4)) | N4: =IF(A4="","",IF(L4="","Sem histórico",IF(AND(L4>=Parametros!$B$2,L4<=EOMONTH(Parametros!$B$2,0)),"Comprou no mês",IF(M4="","Sem periodicidade",IF(M4<Parametros!$B$2,"Atrasado",IF(M4<=EOMONTH(Parametros!$B$2,0),"Previsto no mês","Em dia"))))))
A5: C004 | B5: Cliente Exemplo 04 | C5: Paraguai | D5: Espanhol | E5: Direto | F5: 3 | G5: Ativo | I5: =IF(A5="","",COUNTIFS(Pedidos!$C:$C,A5,Pedidos!$K:$K,Parametros!$B$3)) | J5: =IF(A5="","",SUMIFS(Pedidos!$E:$E,Pedidos!$C:$C,A5,Pedidos!$K:$K,Parametros!$B$3)) | K5: =IF(A5="","",COUNTIFS(Pedidos!$C:$C,A5,Pedidos!$K:$K,Parametros!$B$4)) | L5: =IF(A5="","",IF(COUNTIFS(Pedidos!$C:$C,A5,Pedidos!$B:$B,"<="&EOMONTH(Parametros!$B$2,0))=0,"",_xlfn.MAXIFS(Pedidos!$B:$B,Pedidos!$C:$C,A5,Pedidos!$B:$B,"<="&EOMONTH(Parametros!$B$2,0)))) | M5: =IF(OR(L5="",F5=""),"",EDATE(L5,F5)) | N5: =IF(A5="","",IF(L5="","Sem histórico",IF(AND(L5>=Parametros!$B$2,L5<=EOMONTH(Parametros!$B$2,0)),"Comprou no mês",IF(M5="","Sem periodicidade",IF(M5<Parametros!$B$2,"Atrasado",IF(M5<=EOMONTH(Parametros!$B$2,0),"Previsto no mês","Em dia"))))))
A6: C005 | B6: Cliente Exemplo 05 | C6: Paraguai | D6: Espanhol | E6: Agente LatAm | F6: 1 | G6: Ativo | I6: =IF(A6="","",COUNTIFS(Pedidos!$C:$C,A6,Pedidos!$K:$K,Parametros!$B$3)) | J6: =IF(A6="","",SUMIFS(Pedidos!$E:$E,Pedidos!$C:$C,A6,Pedidos!$K:$K,Parametros!$B$3)) | K6: =IF(A6="","",COUNTIFS(Pedidos!$C:$C,A6,Pedidos!$K:$K,Parametros!$B$4)) | L6: =IF(A6="","",IF(COUNTIFS(Pedidos!$C:$C,A6,Pedidos!$B:$B,"<="&EOMONTH(Parametros!$B$2,0))=0,"",_xlfn.MAXIFS(Pedidos!$B:$B,Pedidos!$C:$C,A6,Pedidos!$B:$B,"<="&EOMONTH(Parametros!$B$2,0)))) | M6: =IF(OR(L6="",F6=""),"",EDATE(L6,F6)) | N6: =IF(A6="","",IF(L6="","Sem histórico",IF(AND(L6>=Parametros!$B$2,L6<=EOMONTH(Parametros!$B$2,0)),"Comprou no mês",IF(M6="","Sem periodicidade",IF(M6<Parametros!$B$2,"Atrasado",IF(M6<=EOMONTH(Parametros!$B$2,0),"Previsto no mês","Em dia"))))))
A7: C006 | B7: Cliente Exemplo 06 | C7: Japão | D7: Japonês | E7: Direto | F7: 1 | G7: Ativo | I7: =IF(A7="","",COUNTIFS(Pedidos!$C:$C,A7,Pedidos!$K:$K,Parametros!$B$3)) | J7: =IF(A7="","",SUMIFS(Pedidos!$E:$E,Pedidos!$C:$C,A7,Pedidos!$K:$K,Parametros!$B$3)) | K7: =IF(A7="","",COUNTIFS(Pedidos!$C:$C,A7,Pedidos!$K:$K,Parametros!$B$4)) | L7: =IF(A7="","",IF(COUNTIFS(Pedidos!$C:$C,A7,Pedidos!$B:$B,"<="&EOMONTH(Parametros!$B$2,0))=0,"",_xlfn.MAXIFS(Pedidos!$B:$B,Pedidos!$C:$C,A7,Pedidos!$B:$B,"<="&EOMONTH(Parametros!$B$2,0)))) | M7: =IF(OR(L7="",F7=""),"",EDATE(L7,F7)) | N7: =IF(A7="","",IF(L7="","Sem histórico",IF(AND(L7>=Parametros!$B$2,L7<=EOMONTH(Parametros!$B$2,0)),"Comprou no mês",IF(M7="","Sem periodicidade",IF(M7<Parametros!$B$2,"Atrasado",IF(M7<=EOMONTH(Parametros!$B$2,0),"Previsto no mês","Em dia"))))))
A8: C007 | B8: Cliente Exemplo 07 | C8: Chile | D8: Espanhol | E8: Agente LatAm | F8: 3 | G8: Ativo | I8: =IF(A8="","",COUNTIFS(Pedidos!$C:$C,A8,Pedidos!$K:$K,Parametros!$B$3)) | J8: =IF(A8="","",SUMIFS(Pedidos!$E:$E,Pedidos!$C:$C,A8,Pedidos!$K:$K,Parametros!$B$3)) | K8: =IF(A8="","",COUNTIFS(Pedidos!$C:$C,A8,Pedidos!$K:$K,Parametros!$B$4)) | L8: =IF(A8="","",IF(COUNTIFS(Pedidos!$C:$C,A8,Pedidos!$B:$B,"<="&EOMONTH(Parametros!$B$2,0))=0,"",_xlfn.MAXIFS(Pedidos!$B:$B,Pedidos!$C:$C,A8,Pedidos!$B:$B,"<="&EOMONTH(Parametros!$B$2,0)))) | M8: =IF(OR(L8="",F8=""),"",EDATE(L8,F8)) | N8: =IF(A8="","",IF(L8="","Sem histórico",IF(AND(L8>=Parametros!$B$2,L8<=EOMONTH(Parametros!$B$2,0)),"Comprou no mês",IF(M8="","Sem periodicidade",IF(M8<Parametros!$B$2,"Atrasado",IF(M8<=EOMONTH(Parametros!$B$2,0),"Previsto no mês","Em dia"))))))
A9: C008 | B9: Cliente Exemplo 08 | C9: Paraguai | D9: Espanhol | E9: Trading | F9: 6 | G9: Ativo | I9: =IF(A9="","",COUNTIFS(Pedidos!$C:$C,A9,Pedidos!$K:$K,Parametros!$B$3)) | J9: =IF(A9="","",SUMIFS(Pedidos!$E:$E,Pedidos!$C:$C,A9,Pedidos!$K:$K,Parametros!$B$3)) | K9: =IF(A9="","",COUNTIFS(Pedidos!$C:$C,A9,Pedidos!$K:$K,Parametros!$B$4)) | L9: =IF(A9="","",IF(COUNTIFS(Pedidos!$C:$C,A9,Pedidos!$B:$B,"<="&EOMONTH(Parametros!$B$2,0))=0,"",_xlfn.MAXIFS(Pedidos!$B:$B,Pedidos!$C:$C,A9,Pedidos!$B:$B,"<="&EOMONTH(Parametros!$B$2,0)))) | M9: =IF(OR(L9="",F9=""),"",EDATE(L9,F9)) | N9: =IF(A9="","",IF(L9="","Sem histórico",IF(AND(L9>=Parametros!$B$2,L9<=EOMONTH(Parametros!$B$2,0)),"Comprou no mês",IF(M9="","Sem periodicidade",IF(M9<Parametros!$B$2,"Atrasado",IF(M9<=EOMONTH(Parametros!$B$2,0),"Previsto no mês","Em dia"))))))
A10: C009 | B10: Cliente Exemplo 09 | C10: Chile | D10: Espanhol | E10: Trading | F10: 2 | G10: Ativo | I10: =IF(A10="","",COUNTIFS(Pedidos!$C:$C,A10,Pedidos!$K:$K,Parametros!$B$3)) | J10: =IF(A10="","",SUMIFS(Pedidos!$E:$E,Pedidos!$C:$C,A10,Pedidos!$K:$K,Parametros!$B$3)) | K10: =IF(A10="","",COUNTIFS(Pedidos!$C:$C,A10,Pedidos!$K:$K,Parametros!$B$4)) | L10: =IF(A10="","",IF(COUNTIFS(Pedidos!$C:$C,A10,Pedidos!$B:$B,"<="&EOMONTH(Parametros!$B$2,0))=0,"",_xlfn.MAXIFS(Pedidos!$B:$B,Pedidos!$C:$C,A10,Pedidos!$B:$B,"<="&EOMONTH(Parametros!$B$2,0)))) | M10: =IF(OR(L10="",F10=""),"",EDATE(L10,F10)) | N10: =IF(A10="","",IF(L10="","Sem histórico",IF(AND(L10>=Parametros!$B$2,L10<=EOMONTH(Parametros!$B$2,0)),"Comprou no mês",IF(M10="","Sem periodicidade",IF(M10<Parametros!$B$2,"Atrasado",IF(M10<=EOMONTH(Parametros!$B$2,0),"Previsto no mês","Em dia"))))))
A11: C010 | B11: Cliente Exemplo 10 | C11: Gana | D11: Inglês | E11: Trading | F11: 1 | G11: Ativo | I11: =IF(A11="","",COUNTIFS(Pedidos!$C:$C,A11,Pedidos!$K:$K,Parametros!$B$3)) | J11: =IF(A11="","",SUMIFS(Pedidos!$E:$E,Pedidos!$C:$C,A11,Pedidos!$K:$K,Parametros!$B$3)) | K11: =IF(A11="","",COUNTIFS(Pedidos!$C:$C,A11,Pedidos!$K:$K,Parametros!$B$4)) | L11: =IF(A11="","",IF(COUNTIFS(Pedidos!$C:$C,A11,Pedidos!$B:$B,"<="&EOMONTH(Parametros!$B$2,0))=0,"",_xlfn.MAXIFS(Pedidos!$B:$B,Pedidos!$C:$C,A11,Pedidos!$B:$B,"<="&EOMONTH(Parametros!$B$2,0)))) | M11: =IF(OR(L11="",F11=""),"",EDATE(L11,F11)) | N11: =IF(A11="","",IF(L11="","Sem histórico",IF(AND(L11>=Parametros!$B$2,L11<=EOMONTH(Parametros!$B$2,0)),"Comprou no mês",IF(M11="","Sem periodicidade",IF(M11<Parametros!$B$2,"Atrasado",IF(M11<=EOMONTH(Parametros!$B$2,0),"Previsto no mês","Em dia"))))))
A12: C011 | B12: Cliente Exemplo 11 | C12: Gana | D12: Inglês | E12: Direto | F12: 3 | G12: Ativo | I12: =IF(A12="","",COUNTIFS(Pedidos!$C:$C,A12,Pedidos!$K:$K,Parametros!$B$3)) | J12: =IF(A12="","",SUMIFS(Pedidos!$E:$E,Pedidos!$C:$C,A12,Pedidos!$K:$K,Parametros!$B$3)) | K12: =IF(A12="","",COUNTIFS(Pedidos!$C:$C,A12,Pedidos!$K:$K,Parametros!$B$4)) | L12: =IF(A12="","",IF(COUNTIFS(Pedidos!$C:$C,A12,Pedidos!$B:$B,"<="&EOMONTH(Parametros!$B$2,0))=0,"",_xlfn.MAXIFS(Pedidos!$B:$B,Pedidos!$C:$C,A12,Pedidos!$B:$B,"<="&EOMONTH(Parametros!$B$2,0)))) | M12: =IF(OR(L12="",F12=""),"",EDATE(L12,F12)) | N12: =IF(A12="","",IF(L12="","Sem histórico",IF(AND(L12>=Parametros!$B$2,L12<=EOMONTH(Parametros!$B$2,0)),"Comprou no mês",IF(M12="","Sem periodicidade",IF(M12<Parametros!$B$2,"Atrasado",IF(M12<=EOMONTH(Parametros!$B$2,0),"Previsto no mês","Em dia"))))))
A13: C012 | B13: Cliente Exemplo 12 | C13: Angola | D13: Português | E13: Trading | F13: 1 | G13: Ativo | I13: =IF(A13="","",COUNTIFS(Pedidos!$C:$C,A13,Pedidos!$K:$K,Parametros!$B$3)) | J13: =IF(A13="","",SUMIFS(Pedidos!$E:$E,Pedidos!$C:$C,A13,Pedidos!$K:$K,Parametros!$B$3)) | K13: =IF(A13="","",COUNTIFS(Pedidos!$C:$C,A13,Pedidos!$K:$K,Parametros!$B$4)) | L13: =IF(A13="","",IF(COUNTIFS(Pedidos!$C:$C,A13,Pedidos!$B:$B,"<="&EOMONTH(Parametros!$B$2,0))=0,"",_xlfn.MAXIFS(Pedidos!$B:$B,Pedidos!$C:$C,A13,Pedidos!$B:$B,"<="&EOMONTH(Parametros!$B$2,0)))) | M13: =IF(OR(L13="",F13=""),"",EDATE(L13,F13)) | N13: =IF(A13="","",IF(L13="","Sem histórico",IF(AND(L13>=Parametros!$B$2,L13<=EOMONTH(Parametros!$B$2,0)),"Comprou no mês",IF(M13="","Sem periodicidade",IF(M13<Parametros!$B$2,"Atrasado",IF(M13<=EOMONTH(Parametros!$B$2,0),"Previsto no mês","Em dia"))))))
... A27: C026 | B27: Cliente Exemplo 26 | C27: Peru | D27: Espanhol | E27: Agente LatAm | F27: 3 | G27: Ativo | I27: =IF(A27="","",COUNTIFS(Pedidos!$C:$C,A27,Pedidos!$K:$K,Parametros!$B$3)) | J27: =IF(A27="","",SUMIFS(Pedidos!$E:$E,Pedidos!$C:$C,A27,Pedidos!$K:$K,Parametros!$B$3)) | K27: =IF(A27="","",COUNTIFS(Pedidos!$C:$C,A27,Pedidos!$K:$K,Parametros!$B$4)) | L27: =IF(A27="","",IF(COUNTIFS(Pedidos!$C:$C,A27,Pedidos!$B:$B,"<="&EOMONTH(Parametros!$B$2,0))=0,"",_xlfn.MAXIFS(Pedidos!$B:$B,Pedidos!$C:$C,A27,Pedidos!$B:$B,"<="&EOMONTH(Parametros!$B$2,0)))) | M27: =IF(OR(L27="",F27=""),"",EDATE(L27,F27)) | N27: =IF(A27="","",IF(L27="","Sem histórico",IF(AND(L27>=Parametros!$B$2,L27<=EOMONTH(Parametros!$B$2,0)),"Comprou no mês",IF(M27="","Sem periodicidade",IF(M27<Parametros!$B$2,"Atrasado",IF(M27<=EOMONTH(Parametros!$B$2,0),"Previsto no mês","Em dia"))))))
I28: =IF(A28="","",COUNTIFS(Pedidos!$C:$C,A28,Pedidos!$K:$K,Parametros!$B$3)) | J28: =IF(A28="","",SUMIFS(Pedidos!$E:$E,Pedidos!$C:$C,A28,Pedidos!$K:$K,Parametros!$B$3)) | K28: =IF(A28="","",COUNTIFS(Pedidos!$C:$C,A28,Pedidos!$K:$K,Parametros!$B$4)) | L28: =IF(A28="","",IF(COUNTIFS(Pedidos!$C:$C,A28,Pedidos!$B:$B,"<="&EOMONTH(Parametros!$B$2,0))=0,"",_xlfn.MAXIFS(Pedidos!$B:$B,Pedidos!$C:$C,A28,Pedidos!$B:$B,"<="&EOMONTH(Parametros!$B$2,0)))) | M28: =IF(OR(L28="",F28=""),"",EDATE(L28,F28)) | N28: =IF(A28="","",IF(L28="","Sem histórico",IF(AND(L28>=Parametros!$B$2,L28<=EOMONTH(Parametros!$B$2,0)),"Comprou no mês",IF(M28="","Sem periodicidade",IF(M28<Parametros!$B$2,"Atrasado",IF(M28<=EOMONTH(Parametros!$B$2,0),"Previsto no mês","Em dia"))))))
I29: =IF(A29="","",COUNTIFS(Pedidos!$C:$C,A29,Pedidos!$K:$K,Parametros!$B$3)) | J29: =IF(A29="","",SUMIFS(Pedidos!$E:$E,Pedidos!$C:$C,A29,Pedidos!$K:$K,Parametros!$B$3)) | K29: =IF(A29="","",COUNTIFS(Pedidos!$C:$C,A29,Pedidos!$K:$K,Parametros!$B$4)) | L29: =IF(A29="","",IF(COUNTIFS(Pedidos!$C:$C,A29,Pedidos!$B:$B,"<="&EOMONTH(Parametros!$B$2,0))=0,"",_xlfn.MAXIFS(Pedidos!$B:$B,Pedidos!$C:$C,A29,Pedidos!$B:$B,"<="&EOMONTH(Parametros!$B$2,0)))) | M29: =IF(OR(L29="",F29=""),"",EDATE(L29,F29)) | N29: =IF(A29="","",IF(L29="","Sem histórico",IF(AND(L29>=Parametros!$B$2,L29<=EOMONTH(Parametros!$B$2,0)),"Comprou no mês",IF(M29="","Sem periodicidade",IF(M29<Parametros!$B$2,"Atrasado",IF(M29<=EOMONTH(Parametros!$B$2,0),"Previsto no mês","Em dia"))))))
I30: =IF(A30="","",COUNTIFS(Pedidos!$C:$C,A30,Pedidos!$K:$K,Parametros!$B$3)) | J30: =IF(A30="","",SUMIFS(Pedidos!$E:$E,Pedidos!$C:$C,A30,Pedidos!$K:$K,Parametros!$B$3)) | K30: =IF(A30="","",COUNTIFS(Pedidos!$C:$C,A30,Pedidos!$K:$K,Parametros!$B$4)) | L30: =IF(A30="","",IF(COUNTIFS(Pedidos!$C:$C,A30,Pedidos!$B:$B,"<="&EOMONTH(Parametros!$B$2,0))=0,"",_xlfn.MAXIFS(Pedidos!$B:$B,Pedidos!$C:$C,A30,Pedidos!$B:$B,"<="&EOMONTH(Parametros!$B$2,0)))) | M30: =IF(OR(L30="",F30=""),"",EDATE(L30,F30)) | N30: =IF(A30="","",IF(L30="","Sem histórico",IF(AND(L30>=Parametros!$B$2,L30<=EOMONTH(Parametros!$B$2,0)),"Comprou no mês",IF(M30="","Sem periodicidade",IF(M30<Parametros!$B$2,"Atrasado",IF(M30<=EOMONTH(Parametros!$B$2,0),"Previsto no mês","Em dia"))))))
I31: =IF(A31="","",COUNTIFS(Pedidos!$C:$C,A31,Pedidos!$K:$K,Parametros!$B$3)) | J31: =IF(A31="","",SUMIFS(Pedidos!$E:$E,Pedidos!$C:$C,A31,Pedidos!$K:$K,Parametros!$B$3)) | K31: =IF(A31="","",COUNTIFS(Pedidos!$C:$C,A31,Pedidos!$K:$K,Parametros!$B$4)) | L31: =IF(A31="","",IF(COUNTIFS(Pedidos!$C:$C,A31,Pedidos!$B:$B,"<="&EOMONTH(Parametros!$B$2,0))=0,"",_xlfn.MAXIFS(Pedidos!$B:$B,Pedidos!$C:$C,A31,Pedidos!$B:$B,"<="&EOMONTH(Parametros!$B$2,0)))) | M31: =IF(OR(L31="",F31=""),"",EDATE(L31,F31)) | N31: =IF(A31="","",IF(L31="","Sem histórico",IF(AND(L31>=Parametros!$B$2,L31<=EOMONTH(Parametros!$B$2,0)),"Comprou no mês",IF(M31="","Sem periodicidade",IF(M31<Parametros!$B$2,"Atrasado",IF(M31<=EOMONTH(Parametros!$B$2,0),"Previsto no mês","Em dia"))))))
I32: =IF(A32="","",COUNTIFS(Pedidos!$C:$C,A32,Pedidos!$K:$K,Parametros!$B$3)) | J32: =IF(A32="","",SUMIFS(Pedidos!$E:$E,Pedidos!$C:$C,A32,Pedidos!$K:$K,Parametros!$B$3)) | K32: =IF(A32="","",COUNTIFS(Pedidos!$C:$C,A32,Pedidos!$K:$K,Parametros!$B$4)) | L32: =IF(A32="","",IF(COUNTIFS(Pedidos!$C:$C,A32,Pedidos!$B:$B,"<="&EOMONTH(Parametros!$B$2,0))=0,"",_xlfn.MAXIFS(Pedidos!$B:$B,Pedidos!$C:$C,A32,Pedidos!$B:$B,"<="&EOMONTH(Parametros!$B$2,0)))) | M32: =IF(OR(L32="",F32=""),"",EDATE(L32,F32)) | N32: =IF(A32="","",IF(L32="","Sem histórico",IF(AND(L32>=Parametros!$B$2,L32<=EOMONTH(Parametros!$B$2,0)),"Comprou no mês",IF(M32="","Sem periodicidade",IF(M32<Parametros!$B$2,"Atrasado",IF(M32<=EOMONTH(Parametros!$B$2,0),"Previsto no mês","Em dia"))))))
I33: =IF(A33="","",COUNTIFS(Pedidos!$C:$C,A33,Pedidos!$K:$K,Parametros!$B$3)) | J33: =IF(A33="","",SUMIFS(Pedidos!$E:$E,Pedidos!$C:$C,A33,Pedidos!$K:$K,Parametros!$B$3)) | K33: =IF(A33="","",COUNTIFS(Pedidos!$C:$C,A33,Pedidos!$K:$K,Parametros!$B$4)) | L33: =IF(A33="","",IF(COUNTIFS(Pedidos!$C:$C,A33,Pedidos!$B:$B,"<="&EOMONTH(Parametros!$B$2,0))=0,"",_xlfn.MAXIFS(Pedidos!$B:$B,Pedidos!$C:$C,A33,Pedidos!$B:$B,"<="&EOMONTH(Parametros!$B$2,0)))) | M33: =IF(OR(L33="",F33=""),"",EDATE(L33,F33)) | N33: =IF(A33="","",IF(L33="","Sem histórico",IF(AND(L33>=Parametros!$B$2,L33<=EOMONTH(Parametros!$B$2,0)),"Comprou no mês",IF(M33="","Sem periodicidade",IF(M33<Parametros!$B$2,"Atrasado",IF(M33<=EOMONTH(Parametros!$B$2,0),"Previsto no mês","Em dia"))))))
I34: =IF(A34="","",COUNTIFS(Pedidos!$C:$C,A34,Pedidos!$K:$K,Parametros!$B$3)) | J34: =IF(A34="","",SUMIFS(Pedidos!$E:$E,Pedidos!$C:$C,A34,Pedidos!$K:$K,Parametros!$B$3)) | K34: =IF(A34="","",COUNTIFS(Pedidos!$C:$C,A34,Pedidos!$K:$K,Parametros!$B$4)) | L34: =IF(A34="","",IF(COUNTIFS(Pedidos!$C:$C,A34,Pedidos!$B:$B,"<="&EOMONTH(Parametros!$B$2,0))=0,"",_xlfn.MAXIFS(Pedidos!$B:$B,Pedidos!$C:$C,A34,Pedidos!$B:$B,"<="&EOMONTH(Parametros!$B$2,0)))) | M34: =IF(OR(L34="",F34=""),"",EDATE(L34,F34)) | N34: =IF(A34="","",IF(L34="","Sem histórico",IF(AND(L34>=Parametros!$B$2,L34<=EOMONTH(Parametros!$B$2,0)),"Comprou no mês",IF(M34="","Sem periodicidade",IF(M34<Parametros!$B$2,"Atrasado",IF(M34<=EOMONTH(Parametros!$B$2,0),"Previsto no mês","Em dia"))))))
I35: =IF(A35="","",COUNTIFS(Pedidos!$C:$C,A35,Pedidos!$K:$K,Parametros!$B$3)) | J35: =IF(A35="","",SUMIFS(Pedidos!$E:$E,Pedidos!$C:$C,A35,Pedidos!$K:$K,Parametros!$B$3)) | K35: =IF(A35="","",COUNTIFS(Pedidos!$C:$C,A35,Pedidos!$K:$K,Parametros!$B$4)) | L35: =IF(A35="","",IF(COUNTIFS(Pedidos!$C:$C,A35,Pedidos!$B:$B,"<="&EOMONTH(Parametros!$B$2,0))=0,"",_xlfn.MAXIFS(Pedidos!$B:$B,Pedidos!$C:$C,A35,Pedidos!$B:$B,"<="&EOMONTH(Parametros!$B$2,0)))) | M35: =IF(OR(L35="",F35=""),"",EDATE(L35,F35)) | N35: =IF(A35="","",IF(L35="","Sem histórico",IF(AND(L35>=Parametros!$B$2,L35<=EOMONTH(Parametros!$B$2,0)),"Comprou no mês",IF(M35="","Sem periodicidade",IF(M35<Parametros!$B$2,"Atrasado",IF(M35<=EOMONTH(Parametros!$B$2,0),"Previsto no mês","Em dia"))))))
I36: =IF(A36="","",COUNTIFS(Pedidos!$C:$C,A36,Pedidos!$K:$K,Parametros!$B$3)) | J36: =IF(A36="","",SUMIFS(Pedidos!$E:$E,Pedidos!$C:$C,A36,Pedidos!$K:$K,Parametros!$B$3)) | K36: =IF(A36="","",COUNTIFS(Pedidos!$C:$C,A36,Pedidos!$K:$K,Parametros!$B$4)) | L36: =IF(A36="","",IF(COUNTIFS(Pedidos!$C:$C,A36,Pedidos!$B:$B,"<="&EOMONTH(Parametros!$B$2,0))=0,"",_xlfn.MAXIFS(Pedidos!$B:$B,Pedidos!$C:$C,A36,Pedidos!$B:$B,"<="&EOMONTH(Parametros!$B$2,0)))) | M36: =IF(OR(L36="",F36=""),"",EDATE(L36,F36)) | N36: =IF(A36="","",IF(L36="","Sem histórico",IF(AND(L36>=Parametros!$B$2,L36<=EOMONTH(Parametros!$B$2,0)),"Comprou no mês",IF(M36="","Sem periodicidade",IF(M36<Parametros!$B$2,"Atrasado",IF(M36<=EOMONTH(Parametros!$B$2,0),"Previsto no mês","Em dia"))))))
I37: =IF(A37="","",COUNTIFS(Pedidos!$C:$C,A37,Pedidos!$K:$K,Parametros!$B$3)) | J37: =IF(A37="","",SUMIFS(Pedidos!$E:$E,Pedidos!$C:$C,A37,Pedidos!$K:$K,Parametros!$B$3)) | K37: =IF(A37="","",COUNTIFS(Pedidos!$C:$C,A37,Pedidos!$K:$K,Parametros!$B$4)) | L37: =IF(A37="","",IF(COUNTIFS(Pedidos!$C:$C,A37,Pedidos!$B:$B,"<="&EOMONTH(Parametros!$B$2,0))=0,"",_xlfn.MAXIFS(Pedidos!$B:$B,Pedidos!$C:$C,A37,Pedidos!$B:$B,"<="&EOMONTH(Parametros!$B$2,0)))) | M37: =IF(OR(L37="",F37=""),"",EDATE(L37,F37)) | N37: =IF(A37="","",IF(L37="","Sem histórico",IF(AND(L37>=Parametros!$B$2,L37<=EOMONTH(Parametros!$B$2,0)),"Comprou no mês",IF(M37="","Sem periodicidade",IF(M37<Parametros!$B$2,"Atrasado",IF(M37<=EOMONTH(Parametros!$B$2,0),"Previsto no mês","Em dia"))))))
I38: =IF(A38="","",COUNTIFS(Pedidos!$C:$C,A38,Pedidos!$K:$K,Parametros!$B$3)) | J38: =IF(A38="","",SUMIFS(Pedidos!$E:$E,Pedidos!$C:$C,A38,Pedidos!$K:$K,Parametros!$B$3)) | K38: =IF(A38="","",COUNTIFS(Pedidos!$C:$C,A38,Pedidos!$K:$K,Parametros!$B$4)) | L38: =IF(A38="","",IF(COUNTIFS(Pedidos!$C:$C,A38,Pedidos!$B:$B,"<="&EOMONTH(Parametros!$B$2,0))=0,"",_xlfn.MAXIFS(Pedidos!$B:$B,Pedidos!$C:$C,A38,Pedidos!$B:$B,"<="&EOMONTH(Parametros!$B$2,0)))) | M38: =IF(OR(L38="",F38=""),"",EDATE(L38,F38)) | N38: =IF(A38="","",IF(L38="","Sem histórico",IF(AND(L38>=Parametros!$B$2,L38<=EOMONTH(Parametros!$B$2,0)),"Comprou no mês",IF(M38="","Sem periodicidade",IF(M38<Parametros!$B$2,"Atrasado",IF(M38<=EOMONTH(Parametros!$B$2,0),"Previsto no mês","Em dia"))))))
I39: =IF(A39="","",COUNTIFS(Pedidos!$C:$C,A39,Pedidos!$K:$K,Parametros!$B$3)) | J39: =IF(A39="","",SUMIFS(Pedidos!$E:$E,Pedidos!$C:$C,A39,Pedidos!$K:$K,Parametros!$B$3)) | K39: =IF(A39="","",COUNTIFS(Pedidos!$C:$C,A39,Pedidos!$K:$K,Parametros!$B$4)) | L39: =IF(A39="","",IF(COUNTIFS(Pedidos!$C:$C,A39,Pedidos!$B:$B,"<="&EOMONTH(Parametros!$B$2,0))=0,"",_xlfn.MAXIFS(Pedidos!$B:$B,Pedidos!$C:$C,A39,Pedidos!$B:$B,"<="&EOMONTH(Parametros!$B$2,0)))) | M39: =IF(OR(L39="",F39=""),"",EDATE(L39,F39)) | N39: =IF(A39="","",IF(L39="","Sem histórico",IF(AND(L39>=Parametros!$B$2,L39<=EOMONTH(Parametros!$B$2,0)),"Comprou no mês",IF(M39="","Sem periodicidade",IF(M39<Parametros!$B$2,"Atrasado",IF(M39<=EOMONTH(Parametros!$B$2,0),"Previsto no mês","Em dia"))))))
... I501: =IF(A501="","",COUNTIFS(Pedidos!$C:$C,A501,Pedidos!$K:$K,Parametros!$B$3)) | J501: =IF(A501="","",SUMIFS(Pedidos!$E:$E,Pedidos!$C:$C,A501,Pedidos!$K:$K,Parametros!$B$3)) | K501: =IF(A501="","",COUNTIFS(Pedidos!$C:$C,A501,Pedidos!$K:$K,Parametros!$B$4)) | L501: =IF(A501="","",IF(COUNTIFS(Pedidos!$C:$C,A501,Pedidos!$B:$B,"<="&EOMONTH(Parametros!$B$2,0))=0,"",_xlfn.MAXIFS(Pedidos!$B:$B,Pedidos!$C:$C,A501,Pedidos!$B:$B,"<="&EOMONTH(Parametros!$B$2,0)))) | M501: =IF(OR(L501="",F501=""),"",EDATE(L501,F501)) | N501: =IF(A501="","",IF(L501="","Sem histórico",IF(AND(L501>=Parametros!$B$2,L501<=EOMONTH(Parametros!$B$2,0)),"Comprou no mês",IF(M501="","Sem periodicidade",IF(M501<Parametros!$B$2,"Atrasado",IF(M501<=EOMONTH(Parametros!$B$2,0),"Previsto no mês","Em dia"))))))

Sheet Pedidos
A1: Nº Pedido | B1: Data do pedido | C1: Cód. Cliente | D1: Produto | E1: Toneladas | F1: Valor (USD) | G1: Incoterm | H1: Embarque negociado | I1: Embarque realizado | J1: Cliente | K1: Ano | L1: Mês | M1: Dias até embarque | N1: Prazo de embarque
A2: PV1001 | B2: 45698 | C2: C001 | D2: Produto A 1kg | E2: 3.7 | F2: 33815.53 | G2: CFR | H2: 45728 | I2: 45730 | J2: =IF(C2="","",IFERROR(INDEX(Clientes!$B:$B,MATCH(C2,Clientes!$A:$A,0)),"Cód. não cadastrado")) | K2: =IF(B2="","",YEAR(B2)) | L2: =IF(B2="","",MONTH(B2)) | M2: =IF(OR(B2="",I2=""),"",I2-B2) | N2: =IF(B2="","",IF(I2="",IF(H2="","",IF(TODAY()>H2,"Atrasado (em aberto)","Em aberto")),IF(I2<=H2,"No prazo","Fora do prazo")))
A3: PV1002 | B3: 45752 | C3: C001 | D3: Produto B 5kg | E3: 3.2 | F3: 45069.71 | G3: CIF | H3: 45782 | I3: 45782 | J3: =IF(C3="","",IFERROR(INDEX(Clientes!$B:$B,MATCH(C3,Clientes!$A:$A,0)),"Cód. não cadastrado")) | K3: =IF(B3="","",YEAR(B3)) | L3: =IF(B3="","",MONTH(B3)) | M3: =IF(OR(B3="",I3=""),"",I3-B3) | N3: =IF(B3="","",IF(I3="",IF(H3="","",IF(TODAY()>H3,"Atrasado (em aberto)","Em aberto")),IF(I3<=H3,"No prazo","Fora do prazo")))
A4: PV1003 | B4: 45827 | C4: C001 | D4: Produto B 5kg | E4: 5 | F4: 30758.03 | G4: CFR | H4: 45857 | I4: 45866 | J4: =IF(C4="","",IFERROR(INDEX(Clientes!$B:$B,MATCH(C4,Clientes!$A:$A,0)),"Cód. não cadastrado")) | K4: =IF(B4="","",YEAR(B4)) | L4: =IF(B4="","",MONTH(B4)) | M4: =IF(OR(B4="",I4=""),"",I4-B4) | N4: =IF(B4="","",IF(I4="",IF(H4="","",IF(TODAY()>H4,"Atrasado (em aberto)","Em aberto")),IF(I4<=H4,"No prazo","Fora do prazo")))
A5: PV1004 | B5: 45888 | C5: C001 | D5: Produto B 5kg | E5: 3.4 | F5: 19211.82 | G5: CFR | H5: 45918 | I5: 45927 | J5: =IF(C5="","",IFERROR(INDEX(Clientes!$B:$B,MATCH(C5,Clientes!$A:$A,0)),"Cód. não cadastrado")) | K5: =IF(B5="","",YEAR(B5)) | L5: =IF(B5="","",MONTH(B5)) | M5: =IF(OR(B5="",I5=""),"",I5-B5) | N5: =IF(B5="","",IF(I5="",IF(H5="","",IF(TODAY()>H5,"Atrasado (em aberto)","Em aberto")),IF(I5<=H5,"No prazo","Fora do prazo")))
A6: PV1005 | B6: 45946 | C6: C001 | D6: Produto C granel 25kg | E6: 3.4 | F6: 47902.17 | G6: CFR | H6: 45976 | I6: 45981 | J6: =IF(C6="","",IFERROR(INDEX(Clientes!$B:$B,MATCH(C6,Clientes!$A:$A,0)),"Cód. não cadastrado")) | K6: =IF(B6="","",YEAR(B6)) | L6: =IF(B6="","",MONTH(B6)) | M6: =IF(OR(B6="",I6=""),"",I6-B6) | N6: =IF(B6="","",IF(I6="",IF(H6="","",IF(TODAY()>H6,"Atrasado (em aberto)","Em aberto")),IF(I6<=H6,"No prazo","Fora do prazo")))
A7: PV1006 | B7: 46012 | C7: C001 | D7: Produto C granel 25kg | E7: 7.9 | F7: 27806.8 | G7: CFR | H7: 46042 | I7: 46044 | J7: =IF(C7="","",IFERROR(INDEX(Clientes!$B:$B,MATCH(C7,Clientes!$A:$A,0)),"Cód. não cadastrado")) | K7: =IF(B7="","",YEAR(B7)) | L7: =IF(B7="","",MONTH(B7)) | M7: =IF(OR(B7="",I7=""),"",I7-B7) | N7: =IF(B7="","",IF(I7="",IF(H7="","",IF(TODAY()>H7,"Atrasado (em aberto)","Em aberto")),IF(I7<=H7,"No prazo","Fora do prazo")))
A8: PV1007 | B8: 46118 | C8: C001 | D8: Produto A 1kg | E8: 6 | F8: 24819.35 | G8: CFR | H8: 46148 | I8: 46150 | J8: =IF(C8="","",IFERROR(INDEX(Clientes!$B:$B,MATCH(C8,Clientes!$A:$A,0)),"Cód. não cadastrado")) | K8: =IF(B8="","",YEAR(B8)) | L8: =IF(B8="","",MONTH(B8)) | M8: =IF(OR(B8="",I8=""),"",I8-B8) | N8: =IF(B8="","",IF(I8="",IF(H8="","",IF(TODAY()>H8,"Atrasado (em aberto)","Em aberto")),IF(I8<=H8,"No prazo","Fora do prazo")))
A9: PV1008 | B9: 46247 | C9: C001 | D9: Produto B 5kg | E9: 3.5 | F9: 35213.43 | G9: CIF | H9: 46277 | I9: 46286 | J9: =IF(C9="","",IFERROR(INDEX(Clientes!$B:$B,MATCH(C9,Clientes!$A:$A,0)),"Cód. não cadastrado")) | K9: =IF(B9="","",YEAR(B9)) | L9: =IF(B9="","",MONTH(B9)) | M9: =IF(OR(B9="",I9=""),"",I9-B9) | N9: =IF(B9="","",IF(I9="",IF(H9="","",IF(TODAY()>H9,"Atrasado (em aberto)","Em aberto")),IF(I9<=H9,"No prazo","Fora do prazo")))
A10: PV1009 | B10: 45662 | C10: C002 | D10: Produto B 5kg | E10: 8.2 | F10: 27528.95 | G10: CFR | H10: 45692 | I10: 45701 | J10: =IF(C10="","",IFERROR(INDEX(Clientes!$B:$B,MATCH(C10,Clientes!$A:$A,0)),"Cód. não cadastrado")) | K10: =IF(B10="","",YEAR(B10)) | L10: =IF(B10="","",MONTH(B10)) | M10: =IF(OR(B10="",I10=""),"",I10-B10) | N10: =IF(B10="","",IF(I10="",IF(H10="","",IF(TODAY()>H10,"Atrasado (em aberto)","Em aberto")),IF(I10<=H10,"No prazo","Fora do prazo")))
A11: PV1010 | B11: 45700 | C11: C002 | D11: Produto B 5kg | E11: 8.7 | F11: 21791.44 | G11: FOB | H11: 45730 | I11: 45735 | J11: =IF(C11="","",IFERROR(INDEX(Clientes!$B:$B,MATCH(C11,Clientes!$A:$A,0)),"Cód. não cadastrado")) | K11: =IF(B11="","",YEAR(B11)) | L11: =IF(B11="","",MONTH(B11)) | M11: =IF(OR(B11="",I11=""),"",I11-B11) | N11: =IF(B11="","",IF(I11="",IF(H11="","",IF(TODAY()>H11,"Atrasado (em aberto)","Em aberto")),IF(I11<=H11,"No prazo","Fora do prazo")))
A12: PV1011 | B12: 45721 | C12: C002 | D12: Produto C granel 25kg | E12: 4.4 | F12: 36823.32 | G12: CIF | H12: 45751 | I12: 45748 | J12: =IF(C12="","",IFERROR(INDEX(Clientes!$B:$B,MATCH(C12,Clientes!$A:$A,0)),"Cód. não cadastrado")) | K12: =IF(B12="","",YEAR(B12)) | L12: =IF(B12="","",MONTH(B12)) | M12: =IF(OR(B12="",I12=""),"",I12-B12) | N12: =IF(B12="","",IF(I12="",IF(H12="","",IF(TODAY()>H12,"Atrasado (em aberto)","Em aberto")),IF(I12<=H12,"No prazo","Fora do prazo")))
A13: PV1012 | B13: 45753 | C13: C002 | D13: Produto B 5kg | E13: 3 | F13: 33852.59 | G13: CFR | H13: 45783 | I13: 45783 | J13: =IF(C13="","",IFERROR(INDEX(Clientes!$B:$B,MATCH(C13,Clientes!$A:$A,0)),"Cód. não cadastrado")) | K13: =IF(B13="","",YEAR(B13)) | L13: =IF(B13="","",MONTH(B13)) | M13: =IF(OR(B13="",I13=""),"",I13-B13) | N13: =IF(B13="","",IF(I13="",IF(H13="","",IF(TODAY()>H13,"Atrasado (em aberto)","Em aberto")),IF(I13<=H13,"No prazo","Fora do prazo")))
... A79: PV1078 | B79: 46237 | C79: C006 | D79: Produto C granel 25kg | E79: 8.1 | F79: 21986.35 | G79: CIF | H79: 46267 | I79: 46269 | J79: =IF(C79="","",IFERROR(INDEX(Clientes!$B:$B,MATCH(C79,Clientes!$A:$A,0)),"Cód. não cadastrado")) | K79: =IF(B79="","",YEAR(B79)) | L79: =IF(B79="","",MONTH(B79)) | M79: =IF(OR(B79="",I79=""),"",I79-B79) | N79: =IF(B79="","",IF(I79="",IF(H79="","",IF(TODAY()>H79,"Atrasado (em aberto)","Em aberto")),IF(I79<=H79,"No prazo","Fora do prazo")))
A80: PV1079 | B80: 46285 | C80: C006 | D80: Produto B 5kg | E80: 7.3 | F80: 37238.58 | G80: CFR | H80: 46315 | J80: =IF(C80="","",IFERROR(INDEX(Clientes!$B:$B,MATCH(C80,Clientes!$A:$A,0)),"Cód. não cadastrado")) | K80: =IF(B80="","",YEAR(B80)) | L80: =IF(B80="","",MONTH(B80)) | M80: =IF(OR(B80="",I80=""),"",I80-B80) | N80: =IF(B80="","",IF(I80="",IF(H80="","",IF(TODAY()>H80,"Atrasado (em aberto)","Em aberto")),IF(I80<=H80,"No prazo","Fora do prazo")))
A81: PV1080 | B81: 45736 | C81: C007 | D81: Produto A 1kg | E81: 3.3 | F81: 52588.03 | G81: CIF | H81: 45766 | I81: 45771 | J81: =IF(C81="","",IFERROR(INDEX(Clientes!$B:$B,MATCH(C81,Clientes!$A:$A,0)),"Cód. não cadastrado")) | K81: =IF(B81="","",YEAR(B81)) | L81: =IF(B81="","",MONTH(B81)) | M81: =IF(OR(B81="",I81=""),"",I81-B81) | N81: =IF(B81="","",IF(I81="",IF(H81="","",IF(TODAY()>H81,"Atrasado (em aberto)","Em aberto")),IF(I81<=H81,"No prazo","Fora do prazo")))
A82: PV1081 | B82: 45829 | C82: C007 | D82: Produto C granel 25kg | E82: 7.2 | F82: 37749.35 | G82: CIF | H82: 45859 | I82: 45859 | J82: =IF(C82="","",IFERROR(INDEX(Clientes!$B:$B,MATCH(C82,Clientes!$A:$A,0)),"Cód. não cadastrado")) | K82: =IF(B82="","",YEAR(B82)) | L82: =IF(B82="","",MONTH(B82)) | M82: =IF(OR(B82="",I82=""),"",I82-B82) | N82: =IF(B82="","",IF(I82="",IF(H82="","",IF(TODAY()>H82,"Atrasado (em aberto)","Em aberto")),IF(I82<=H82,"No prazo","Fora do prazo")))
A83: PV1082 | B83: 45925 | C83: C007 | D83: Produto C granel 25kg | E83: 8 | F83: 51210.49 | G83: CIF | H83: 45955 | I83: 45957 | J83: =IF(C83="","",IFERROR(INDEX(Clientes!$B:$B,MATCH(C83,Clientes!$A:$A,0)),"Cód. não cadastrado")) | K83: =IF(B83="","",YEAR(B83)) | L83: =IF(B83="","",MONTH(B83)) | M83: =IF(OR(B83="",I83=""),"",I83-B83) | N83: =IF(B83="","",IF(I83="",IF(H83="","",IF(TODAY()>H83,"Atrasado (em aberto)","Em aberto")),IF(I83<=H83,"No prazo","Fora do prazo")))
A84: PV1083 | B84: 46010 | C84: C007 | D84: Produto C granel 25kg | E84: 7.1 | F84: 46199.68 | G84: FOB | H84: 46040 | I84: 46049 | J84: =IF(C84="","",IFERROR(INDEX(Clientes!$B:$B,MATCH(C84,Clientes!$A:$A,0)),"Cód. não cadastrado")) | K84: =IF(B84="","",YEAR(B84)) | L84: =IF(B84="","",MONTH(B84)) | M84: =IF(OR(B84="",I84=""),"",I84-B84) | N84: =IF(B84="","",IF(I84="",IF(H84="","",IF(TODAY()>H84,"Atrasado (em aberto)","Em aberto")),IF(I84<=H84,"No prazo","Fora do prazo")))
A85: PV1084 | B85: 46207 | C85: C007 | D85: Produto B 5kg | E85: 6.4 | F85: 43249.52 | G85: CIF | H85: 46237 | I85: 46237 | J85: =IF(C85="","",IFERROR(INDEX(Clientes!$B:$B,MATCH(C85,Clientes!$A:$A,0)),"Cód. não cadastrado")) | K85: =IF(B85="","",YEAR(B85)) | L85: =IF(B85="","",MONTH(B85)) | M85: =IF(OR(B85="",I85=""),"",I85-B85) | N85: =IF(B85="","",IF(I85="",IF(H85="","",IF(TODAY()>H85,"Atrasado (em aberto)","Em aberto")),IF(I85<=H85,"No prazo","Fora do prazo")))
A86: PV1085 | B86: 45799 | C86: C008 | D86: Produto B 5kg | E86: 4.6 | F86: 35562.68 | G86: FOB | H86: 45829 | I86: 45826 | J86: =IF(C86="","",IFERROR(INDEX(Clientes!$B:$B,MATCH(C86,Clientes!$A:$A,0)),"Cód. não cadastrado")) | K86: =IF(B86="","",YEAR(B86)) | L86: =IF(B86="","",MONTH(B86)) | M86: =IF(OR(B86="",I86=""),"",I86-B86) | N86: =IF(B86="","",IF(I86="",IF(H86="","",IF(TODAY()>H86,"Atrasado (em aberto)","Em aberto")),IF(I86<=H86,"No prazo","Fora do prazo")))
A87: PV1086 | B87: 45985 | C87: C008 | D87: Produto C granel 25kg | E87: 3.6 | F87: 38669.56 | G87: CIF | H87: 46015 | I87: 46017 | J87: =IF(C87="","",IFERROR(INDEX(Clientes!$B:$B,MATCH(C87,Clientes!$A:$A,0)),"Cód. não cadastrado")) | K87: =IF(B87="","",YEAR(B87)) | L87: =IF(B87="","",MONTH(B87)) | M87: =IF(OR(B87="",I87=""),"",I87-B87) | N87: =IF(B87="","",IF(I87="",IF(H87="","",IF(TODAY()>H87,"Atrasado (em aberto)","Em aberto")),IF(I87<=H87,"No prazo","Fora do prazo")))
A88: PV1087 | B88: 46199 | C88: C008 | D88: Produto B 5kg | E88: 4.4 | F88: 49039.86 | G88: FOB | H88: 46229 | I88: 46223 | J88: =IF(C88="","",IFERROR(INDEX(Clientes!$B:$B,MATCH(C88,Clientes!$A:$A,0)),"Cód. não cadastrado")) | K88: =IF(B88="","",YEAR(B88)) | L88: =IF(B88="","",MONTH(B88)) | M88: =IF(OR(B88="",I88=""),"",I88-B88) | N88: =IF(B88="","",IF(I88="",IF(H88="","",IF(TODAY()>H88,"Atrasado (em aberto)","Em aberto")),IF(I88<=H88,"No prazo","Fora do prazo")))
A89: PV1088 | B89: 45704 | C89: C009 | D89: Produto B 5kg | E89: 3.5 | F89: 55971 | G89: CFR | H89: 45734 | I89: 45743 | J89: =IF(C89="","",IFERROR(INDEX(Clientes!$B:$B,MATCH(C89,Clientes!$A:$A,0)),"Cód. não cadastrado")) | K89: =IF(B89="","",YEAR(B89)) | L89: =IF(B89="","",MONTH(B89)) | M89: =IF(OR(B89="",I89=""),"",I89-B89) | N89: =IF(B89="","",IF(I89="",IF(H89="","",IF(TODAY()>H89,"Atrasado (em aberto)","Em aberto")),IF(I89<=H89,"No prazo","Fora do prazo")))
A90: PV1089 | B90: 45772 | C90: C009 | D90: Produto C granel 25kg | E90: 6.8 | F90: 23923.06 | G90: CIF | H90: 45802 | I90: 45796 | J90: =IF(C90="","",IFERROR(INDEX(Clientes!$B:$B,MATCH(C90,Clientes!$A:$A,0)),"Cód. não cadastrado")) | K90: =IF(B90="","",YEAR(B90)) | L90: =IF(B90="","",MONTH(B90)) | M90: =IF(OR(B90="",I90=""),"",I90-B90) | N90: =IF(B90="","",IF(I90="",IF(H90="","",IF(TODAY()>H90,"Atrasado (em aberto)","Em aberto")),IF(I90<=H90,"No prazo","Fora do prazo")))
A91: PV1090 | B91: 45813 | C91: C009 | D91: Produto B 5kg | E91: 6.9 | F91: 46179.91 | G91: CIF | H91: 45843 | I91: 45843 | J91: =IF(C91="","",IFERROR(INDEX(Clientes!$B:$B,MATCH(C91,Clientes!$A:$A,0)),"Cód. não cadastrado")) | K91: =IF(B91="","",YEAR(B91)) | L91: =IF(B91="","",MONTH(B91)) | M91: =IF(OR(B91="",I91=""),"",I91-B91) | N91: =IF(B91="","",IF(I91="",IF(H91="","",IF(TODAY()>H91,"Atrasado (em aberto)","Em aberto")),IF(I91<=H91,"No prazo","Fora do prazo")))
A92: PV1091 | B92: 45888 | C92: C009 | D92: Produto A 1kg | E92: 5.9 | F92: 36860.91 | G92: CIF | H92: 45918 | I92: 45915 | J92: =IF(C92="","",IFERROR(INDEX(Clientes!$B:$B,MATCH(C92,Clientes!$A:$A,0)),"Cód. não cadastrado")) | K92: =IF(B92="","",YEAR(B92)) | L92: =IF(B92="","",MONTH(B92)) | M92: =IF(OR(B92="",I92=""),"",I92-B92) | N92: =IF(B92="","",IF(I92="",IF(H92="","",IF(TODAY()>H92,"Atrasado (em aberto)","Em aberto")),IF(I92<=H92,"No prazo","Fora do prazo")))
... A96: PV1095 | B96: 46096 | C96: C009 | D96: Produto B 5kg | E96: 4.3 | F96: 57551.43 | G96: FOB | H96: 46126 | I96: 46126 | J96: =IF(C96="","",IFERROR(INDEX(Clientes!$B:$B,MATCH(C96,Clientes!$A:$A,0)),"Cód. não cadastrado")) | K96: =IF(B96="","",YEAR(B96)) | L96: =IF(B96="","",MONTH(B96)) | M96: =IF(OR(B96="",I96=""),"",I96-B96) | N96: =IF(B96="","",IF(I96="",IF(H96="","",IF(TODAY()>H96,"Atrasado (em aberto)","Em aberto")),IF(I96<=H96,"No prazo","Fora do prazo")))
A97: PV1096 | B97: 46274 | C97: C009 | D97: Produto A 1kg | E97: 6.6 | F97: 43425.07 | G97: CFR | H97: 46304 | J97: =IF(C97="","",IFERROR(INDEX(Clientes!$B:$B,MATCH(C97,Clientes!$A:$A,0)),"Cód. não cadastrado")) | K97: =IF(B97="","",YEAR(B97)) | L97: =IF(B97="","",MONTH(B97)) | M97: =IF(OR(B97="",I97=""),"",I97-B97) | N97: =IF(B97="","",IF(I97="",IF(H97="","",IF(TODAY()>H97,"Atrasado (em aberto)","Em aberto")),IF(I97<=H97,"No prazo","Fora do prazo")))
A98: PV1097 | B98: 45680 | C98: C010 | D98: Produto A 1kg | E98: 6 | F98: 54426.54 | G98: CFR | H98: 45710 | I98: 45710 | J98: =IF(C98="","",IFERROR(INDEX(Clientes!$B:$B,MATCH(C98,Clientes!$A:$A,0)),"Cód. não cadastrado")) | K98: =IF(B98="","",YEAR(B98)) | L98: =IF(B98="","",MONTH(B98)) | M98: =IF(OR(B98="",I98=""),"",I98-B98) | N98: =IF(B98="","",IF(I98="",IF(H98="","",IF(TODAY()>H98,"Atrasado (em aberto)","Em aberto")),IF(I98<=H98,"No prazo","Fora do prazo")))
A99: PV1098 | B99: 45689 | C99: C010 | D99: Produto A 1kg | E99: 8.7 | F99: 45671.47 | G99: CFR | H99: 45719 | I99: 45716 | J99: =IF(C99="","",IFERROR(INDEX(Clientes!$B:$B,MATCH(C99,Clientes!$A:$A,0)),"Cód. não cadastrado")) | K99: =IF(B99="","",YEAR(B99)) | L99: =IF(B99="","",MONTH(B99)) | M99: =IF(OR(B99="",I99=""),"",I99-B99) | N99: =IF(B99="","",IF(I99="",IF(H99="","",IF(TODAY()>H99,"Atrasado (em aberto)","Em aberto")),IF(I99<=H99,"No prazo","Fora do prazo")))
A100: PV1099 | B100: 45726 | C100: C010 | D100: Produto A 1kg | E100: 5.5 | F100: 31924.78 | G100: FOB | H100: 45756 | I100: 45761 | J100: =IF(C100="","",IFERROR(INDEX(Clientes!$B:$B,MATCH(C100,Clientes!$A:$A,0)),"Cód. não cadastrado")) | K100: =IF(B100="","",YEAR(B100)) | L100: =IF(B100="","",MONTH(B100)) | M100: =IF(OR(B100="",I100=""),"",I100-B100) | N100: =IF(B100="","",IF(I100="",IF(H100="","",IF(TODAY()>H100,"Atrasado (em aberto)","Em aberto")),IF(I100<=H100,"No prazo","Fora do prazo")))
A101: PV1100 | B101: 45758 | C101: C010 | D101: Produto B 5kg | E101: 7.5 | F101: 52759.99 | G101: FOB | H101: 45788 | I101: 45782 | J101: =IF(C101="","",IFERROR(INDEX(Clientes!$B:$B,MATCH(C101,Clientes!$A:$A,0)),"Cód. não cadastrado")) | K101: =IF(B101="","",YEAR(B101)) | L101: =IF(B101="","",MONTH(B101)) | M101: =IF(OR(B101="",I101=""),"",I101-B101) | N101: =IF(B101="","",IF(I101="",IF(H101="","",IF(TODAY()>H101,"Atrasado (em aberto)","Em aberto")),IF(I101<=H101,"No prazo","Fora do prazo")))
A102: PV1101 | B102: 45784 | C102: C010 | D102: Produto A 1kg | E102: 8.4 | F102: 28042.48 | G102: CFR | H102: 45814 | I102: 45819 | J102: =IF(C102="","",IFERROR(INDEX(Clientes!$B:$B,MATCH(C102,Clientes!$A:$A,0)),"Cód. não cadastrado")) | K102: =IF(B102="","",YEAR(B102)) | L102: =IF(B102="","",MONTH(B102)) | M102: =IF(OR(B102="",I102=""),"",I102-B102) | N102: =IF(B102="","",IF(I102="",IF(H102="","",IF(TODAY()>H102,"Atrasado (em aberto)","Em aberto")),IF(I102<=H102,"No prazo","Fora do prazo")))
A103: PV1102 | B103: 45811 | C103: C010 | D103: Produto B 5kg | E103: 9 | F103: 41512.95 | G103: CFR | H103: 45841 | I103: 45841 | J103: =IF(C103="","",IFERROR(INDEX(Clientes!$B:$B,MATCH(C103,Clientes!$A:$A,0)),"Cód. não cadastrado")) | K103: =IF(B103="","",YEAR(B103)) | L103: =IF(B103="","",MONTH(B103)) | M103: =IF(OR(B103="",I103=""),"",I103-B103) | N103: =IF(B103="","",IF(I103="",IF(H103="","",IF(TODAY()>H103,"Atrasado (em aberto)","Em aberto")),IF(I103<=H103,"No prazo","Fora do prazo")))
A104: PV1103 | B104: 45852 | C104: C010 | D104: Produto B 5kg | E104: 8.1 | F104: 27628.7 | G104: FOB | H104: 45882 | I104: 45891 | J104: =IF(C104="","",IFERROR(INDEX(Clientes!$B:$B,MATCH(C104,Clientes!$A:$A,0)),"Cód. não cadastrado")) | K104: =IF(B104="","",YEAR(B104)) | L104: =IF(B104="","",MONTH(B104)) | M104: =IF(OR(B104="",I104=""),"",I104-B104) | N104: =IF(B104="","",IF(I104="",IF(H104="","",IF(TODAY()>H104,"Atrasado (em aberto)","Em aberto")),IF(I104<=H104,"No prazo","Fora do prazo")))
A105: PV1104 | B105: 45891 | C105: C010 | D105: Produto C granel 25kg | E105: 8.6 | F105: 26219.61 | G105: CFR | H105: 45921 | I105: 45921 | J105: =IF(C105="","",IFERROR(INDEX(Clientes!$B:$B,MATCH(C105,Clientes!$A:$A,0)),"Cód. não cadastrado")) | K105: =IF(B105="","",YEAR(B105)) | L105: =IF(B105="","",MONTH(B105)) | M105: =IF(OR(B105="",I105=""),"",I105-B105) | N105: =IF(B105="","",IF(I105="",IF(H105="","",IF(TODAY()>H105,"Atrasado (em aberto)","Em aberto")),IF(I105<=H105,"No prazo","Fora do prazo")))
A106: PV1105 | B106: 45914 | C106: C010 | D106: Produto B 5kg | E106: 4.1 | F106: 31800.72 | G106: CFR | H106: 45944 | I106: 45946 | J106: =IF(C106="","",IFERROR(INDEX(Clientes!$B:$B,MATCH(C106,Clientes!$A:$A,0)),"Cód. não cadastrado")) | K106: =IF(B106="","",YEAR(B106)) | L106: =IF(B106="","",MONTH(B106)) | M106: =IF(OR(B106="",I106=""),"",I106-B106) | N106: =IF(B106="","",IF(I106="",IF(H106="","",IF(TODAY()>H106,"Atrasado (em aberto)","Em aberto")),IF(I106<=H106,"No prazo","Fora do prazo")))
A107: PV1106 | B107: 45931 | C107: C010 | D107: Produto C granel 25kg | E107: 5.4 | F107: 54407.69 | G107: CIF | H107: 45961 | I107: 45970 | J107: =IF(C107="","",IFERROR(INDEX(Clientes!$B:$B,MATCH(C107,Clientes!$A:$A,0)),"Cód. não cadastrado")) | K107: =IF(B107="","",YEAR(B107)) | L107: =IF(B107="","",MONTH(B107)) | M107: =IF(OR(B107="",I107=""),"",I107-B107) | N107: =IF(B107="","",IF(I107="",IF(H107="","",IF(TODAY()>H107,"Atrasado (em aberto)","Em aberto")),IF(I107<=H107,"No prazo","Fora do prazo")))
A108: PV1107 | B108: 45979 | C108: C010 | D108: Produto C granel 25kg | E108: 3.5 | F108: 57005.94 | G108: CFR | H108: 46009 | I108: 46006 | J108: =IF(C108="","",IFERROR(INDEX(Clientes!$B:$B,MATCH(C108,Clientes!$A:$A,0)),"Cód. não cadastrado")) | K108: =IF(B108="","",YEAR(B108)) | L108: =IF(B108="","",MONTH(B108)) | M108: =IF(OR(B108="",I108=""),"",I108-B108) | N108: =IF(B108="","",IF(I108="",IF(H108="","",IF(TODAY()>H108,"Atrasado (em aberto)","Em aberto")),IF(I108<=H108,"No prazo","Fora do prazo")))
A109: PV1108 | B109: 46006 | C109: C010 | D109: Produto A 1kg | E109: 6.9 | F109: 27879.37 | G109: FOB | H109: 46036 | I109: 46038 | J109: =IF(C109="","",IFERROR(INDEX(Clientes!$B:$B,MATCH(C109,Clientes!$A:$A,0)),"Cód. não cadastrado")) | K109: =IF(B109="","",YEAR(B109)) | L109: =IF(B109="","",MONTH(B109)) | M109: =IF(OR(B109="",I109=""),"",I109-B109) | N109: =IF(B109="","",IF(I109="",IF(H109="","",IF(TODAY()>H109,"Atrasado (em aberto)","Em aberto")),IF(I109<=H109,"No prazo","Fora do prazo")))
... A114: PV1113 | B114: 46206 | C114: C010 | D114: Produto A 1kg | E114: 5.2 | F114: 51421.13 | G114: FOB | H114: 46236 | I114: 46236 | J114: =IF(C114="","",IFERROR(INDEX(Clientes!$B:$B,MATCH(C114,Clientes!$A:$A,0)),"Cód. não cadastrado")) | K114: =IF(B114="","",YEAR(B114)) | L114: =IF(B114="","",MONTH(B114)) | M114: =IF(OR(B114="",I114=""),"",I114-B114) | N114: =IF(B114="","",IF(I114="",IF(H114="","",IF(TODAY()>H114,"Atrasado (em aberto)","Em aberto")),IF(I114<=H114,"No prazo","Fora do prazo")))
A115: PV1114 | B115: 46258 | C115: C010 | D115: Produto B 5kg | E115: 5.3 | F115: 48562.82 | G115: FOB | H115: 46288 | J115: =IF(C115="","",IFERROR(INDEX(Clientes!$B:$B,MATCH(C115,Clientes!$A:$A,0)),"Cód. não cadastrado")) | K115: =IF(B115="","",YEAR(B115)) | L115: =IF(B115="","",MONTH(B115)) | M115: =IF(OR(B115="",I115=""),"",I115-B115) | N115: =IF(B115="","",IF(I115="",IF(H115="","",IF(TODAY()>H115,"Atrasado (em aberto)","Em aberto")),IF(I115<=H115,"No prazo","Fora do prazo")))
A116: PV1115 | B116: 46276 | C116: C010 | D116: Produto A 1kg | E116: 6 | F116: 40842.63 | G116: CFR | H116: 46306 | J116: =IF(C116="","",IFERROR(INDEX(Clientes!$B:$B,MATCH(C116,Clientes!$A:$A,0)),"Cód. não cadastrado")) | K116: =IF(B116="","",YEAR(B116)) | L116: =IF(B116="","",MONTH(B116)) | M116: =IF(OR(B116="",I116=""),"",I116-B116) | N116: =IF(B116="","",IF(I116="",IF(H116="","",IF(TODAY()>H116,"Atrasado (em aberto)","Em aberto")),IF(I116<=H116,"No prazo","Fora do prazo")))
A117: PV1116 | B117: 45679 | C117: C011 | D117: Produto C granel 25kg | E117: 6.8 | F117: 53828.76 | G117: FOB | H117: 45709 | I117: 45711 | J117: =IF(C117="","",IFERROR(INDEX(Clientes!$B:$B,MATCH(C117,Clientes!$A:$A,0)),"Cód. não cadastrado")) | K117: =IF(B117="","",YEAR(B117)) | L117: =IF(B117="","",MONTH(B117)) | M117: =IF(OR(B117="",I117=""),"",I117-B117) | N117: =IF(B117="","",IF(I117="",IF(H117="","",IF(TODAY()>H117,"Atrasado (em aberto)","Em aberto")),IF(I117<=H117,"No prazo","Fora do prazo")))
A118: PV1117 | B118: 45750 | C118: C011 | D118: Produto A 1kg | E118: 5.3 | F118: 44060.63 | G118: CFR | H118: 45780 | I118: 45780 | J118: =IF(C118="","",IFERROR(INDEX(Clientes!$B:$B,MATCH(C118,Clientes!$A:$A,0)),"Cód. não cadastrado")) | K118: =IF(B118="","",YEAR(B118)) | L118: =IF(B118="","",MONTH(B118)) | M118: =IF(OR(B118="",I118=""),"",I118-B118) | N118: =IF(B118="","",IF(I118="",IF(H118="","",IF(TODAY()>H118,"Atrasado (em aberto)","Em aberto")),IF(I118<=H118,"No prazo","Fora do prazo")))
A119: PV1118 | B119: 45848 | C119: C011 | D119: Produto A 1kg | E119: 3.8 | F119: 34133.99 | G119: CFR | H119: 45878 | I119: 45887 | J119: =IF(C119="","",IFERROR(INDEX(Clientes!$B:$B,MATCH(C119,Clientes!$A:$A,0)),"Cód. não cadastrado")) | K119: =IF(B119="","",YEAR(B119)) | L119: =IF(B119="","",MONTH(B119)) | M119: =IF(OR(B119="",I119=""),"",I119-B119) | N119: =IF(B119="","",IF(I119="",IF(H119="","",IF(TODAY()>H119,"Atrasado (em aberto)","Em aberto")),IF(I119<=H119,"No prazo","Fora do prazo")))
A120: PV1119 | B120: 45949 | C120: C011 | D120: Produto A 1kg | E120: 3.4 | F120: 56860.73 | G120: CIF | H120: 45979 | I120: 45979 | J120: =IF(C120="","",IFERROR(INDEX(Clientes!$B:$B,MATCH(C120,Clientes!$A:$A,0)),"Cód. não cadastrado")) | K120: =IF(B120="","",YEAR(B120)) | L120: =IF(B120="","",MONTH(B120)) | M120: =IF(OR(B120="",I120=""),"",I120-B120) | N120: =IF(B120="","",IF(I120="",IF(H120="","",IF(TODAY()>H120,"Atrasado (em aberto)","Em aberto")),IF(I120<=H120,"No prazo","Fora do prazo")))
A121: PV1120 | B121: 46061 | C121: C011 | D121: Produto A 1kg | E121: 4.3 | F121: 21843.07 | G121: CIF | H121: 46091 | I121: 46100 | J121: =IF(C121="","",IFERROR(INDEX(Clientes!$B:$B,MATCH(C121,Clientes!$A:$A,0)),"Cód. não cadastrado")) | K121: =IF(B121="","",YEAR(B121)) | L121: =IF(B121="","",MONTH(B121)) | M121: =IF(OR(B121="",I121=""),"",I121-B121) | N121: =IF(B121="","",IF(I121="",IF(H121="","",IF(TODAY()>H121,"Atrasado (em aberto)","Em aberto")),IF(I121<=H121,"No prazo","Fora do prazo")))
A122: PV1121 | B122: 46257 | C122: C011 | D122: Produto B 5kg | E122: 3.5 | F122: 49958.77 | G122: FOB | H122: 46287 | I122: 46292 | J122: =IF(C122="","",IFERROR(INDEX(Clientes!$B:$B,MATCH(C122,Clientes!$A:$A,0)),"Cód. não cadastrado")) | K122: =IF(B122="","",YEAR(B122)) | L122: =IF(B122="","",MONTH(B122)) | M122: =IF(OR(B122="",I122=""),"",I122-B122) | N122: =IF(B122="","",IF(I122="",IF(H122="","",IF(TODAY()>H122,"Atrasado (em aberto)","Em aberto")),IF(I122<=H122,"No prazo","Fora do prazo")))
A123: PV1122 | B123: 45665 | C123: C012 | D123: Produto A 1kg | E123: 6.9 | F123: 28670.2 | G123: FOB | H123: 45695 | I123: 45697 | J123: =IF(C123="","",IFERROR(INDEX(Clientes!$B:$B,MATCH(C123,Clientes!$A:$A,0)),"Cód. não cadastrado")) | K123: =IF(B123="","",YEAR(B123)) | L123: =IF(B123="","",MONTH(B123)) | M123: =IF(OR(B123="",I123=""),"",I123-B123) | N123: =IF(B123="","",IF(I123="",IF(H123="","",IF(TODAY()>H123,"Atrasado (em aberto)","Em aberto")),IF(I123<=H123,"No prazo","Fora do prazo")))
A124: PV1123 | B124: 45709 | C124: C012 | D124: Produto C granel 25kg | E124: 6.8 | F124: 46436.19 | G124: FOB | H124: 45739 | I124: 45739 | J124: =IF(C124="","",IFERROR(INDEX(Clientes!$B:$B,MATCH(C124,Clientes!$A:$A,0)),"Cód. não cadastrado")) | K124: =IF(B124="","",YEAR(B124)) | L124: =IF(B124="","",MONTH(B124)) | M124: =IF(OR(B124="",I124=""),"",I124-B124) | N124: =IF(B124="","",IF(I124="",IF(H124="","",IF(TODAY()>H124,"Atrasado (em aberto)","Em aberto")),IF(I124<=H124,"No prazo","Fora do prazo")))
A125: PV1124 | B125: 45720 | C125: C012 | D125: Produto B 5kg | E125: 6.1 | F125: 41230.09 | G125: CFR | H125: 45750 | I125: 45744 | J125: =IF(C125="","",IFERROR(INDEX(Clientes!$B:$B,MATCH(C125,Clientes!$A:$A,0)),"Cód. não cadastrado")) | K125: =IF(B125="","",YEAR(B125)) | L125: =IF(B125="","",MONTH(B125)) | M125: =IF(OR(B125="",I125=""),"",I125-B125) | N125: =IF(B125="","",IF(I125="",IF(H125="","",IF(TODAY()>H125,"Atrasado (em aberto)","Em aberto")),IF(I125<=H125,"No prazo","Fora do prazo")))
A126: PV1125 | B126: 45756 | C126: C012 | D126: Produto C granel 25kg | E126: 3 | F126: 39186.43 | G126: CFR | H126: 45786 | I126: 45783 | J126: =IF(C126="","",IFERROR(INDEX(Clientes!$B:$B,MATCH(C126,Clientes!$A:$A,0)),"Cód. não cadastrado")) | K126: =IF(B126="","",YEAR(B126)) | L126: =IF(B126="","",MONTH(B126)) | M126: =IF(OR(B126="",I126=""),"",I126-B126) | N126: =IF(B126="","",IF(I126="",IF(H126="","",IF(TODAY()>H126,"Atrasado (em aberto)","Em aberto")),IF(I126<=H126,"No prazo","Fora do prazo")))
A127: PV1126 | B127: 45786 | C127: C012 | D127: Produto C granel 25kg | E127: 8 | F127: 25906.09 | G127: CIF | H127: 45816 | I127: 45816 | J127: =IF(C127="","",IFERROR(INDEX(Clientes!$B:$B,MATCH(C127,Clientes!$A:$A,0)),"Cód. não cadastrado")) | K127: =IF(B127="","",YEAR(B127)) | L127: =IF(B127="","",MONTH(B127)) | M127: =IF(OR(B127="",I127=""),"",I127-B127) | N127: =IF(B127="","",IF(I127="",IF(H127="","",IF(TODAY()>H127,"Atrasado (em aberto)","Em aberto")),IF(I127<=H127,"No prazo","Fora do prazo")))
A128: PV1127 | B128: 45816 | C128: C012 | D128: Produto A 1kg | E128: 3.2 | F128: 33531.46 | G128: CIF | H128: 45846 | I128: 45848 | J128: =IF(C128="","",IFERROR(INDEX(Clientes!$B:$B,MATCH(C128,Clientes!$A:$A,0)),"Cód. não cadastrado")) | K128: =IF(B128="","",YEAR(B128)) | L128: =IF(B128="","",MONTH(B128)) | M128: =IF(OR(B128="",I128=""),"",I128-B128) | N128: =IF(B128="","",IF(I128="",IF(H128="","",IF(TODAY()>H128,"Atrasado (em aberto)","Em aberto")),IF(I128<=H128,"No prazo","Fora do prazo")))
... A140: PV1139 | B140: 46238 | C140: C012 | D140: Produto A 1kg | E140: 5.3 | F140: 49592.94 | G140: CFR | H140: 46268 | I140: 46270 | J140: =IF(C140="","",IFERROR(INDEX(Clientes!$B:$B,MATCH(C140,Clientes!$A:$A,0)),"Cód. não cadastrado")) | K140: =IF(B140="","",YEAR(B140)) | L140: =IF(B140="","",MONTH(B140)) | M140: =IF(OR(B140="",I140=""),"",I140-B140) | N140: =IF(B140="","",IF(I140="",IF(H140="","",IF(TODAY()>H140,"Atrasado (em aberto)","Em aberto")),IF(I140<=H140,"No prazo","Fora do prazo")))
A141: PV1140 | B141: 46279 | C141: C012 | D141: Produto A 1kg | E141: 7.2 | F141: 23807.21 | G141: CIF | H141: 46309 | J141: =IF(C141="","",IFERROR(INDEX(Clientes!$B:$B,MATCH(C141,Clientes!$A:$A,0)),"Cód. não cadastrado")) | K141: =IF(B141="","",YEAR(B141)) | L141: =IF(B141="","",MONTH(B141)) | M141: =IF(OR(B141="",I141=""),"",I141-B141) | N141: =IF(B141="","",IF(I141="",IF(H141="","",IF(TODAY()>H141,"Atrasado (em aberto)","Em aberto")),IF(I141<=H141,"No prazo","Fora do prazo")))
A142: PV1141 | B142: 45695 | C142: C013 | D142: Produto B 5kg | E142: 7.4 | F142: 36354.05 | G142: CIF | H142: 45725 | I142: 45725 | J142: =IF(C142="","",IFERROR(INDEX(Clientes!$B:$B,MATCH(C142,Clientes!$A:$A,0)),"Cód. não cadastrado")) | K142: =IF(B142="","",YEAR(B142)) | L142: =IF(B142="","",MONTH(B142)) | M142: =IF(OR(B142="",I142=""),"",I142-B142) | N142: =IF(B142="","",IF(I142="",IF(H142="","",IF(TODAY()>H142,"Atrasado (em aberto)","Em aberto")),IF(I142<=H142,"No prazo","Fora do prazo")))
A143: PV1142 | B143: 45761 | C143: C013 | D143: Produto C granel 25kg | E143: 7.6 | F143: 16829.23 | G143: FOB | H143: 45791 | I143: 45788 | J143: =IF(C143="","",IFERROR(INDEX(Clientes!$B:$B,MATCH(C143,Clientes!$A:$A,0)),"Cód. não cadastrado")) | K143: =IF(B143="","",YEAR(B143)) | L143: =IF(B143="","",MONTH(B143)) | M143: =IF(OR(B143="",I143=""),"",I143-B143) | N143: =IF(B143="","",IF(I143="",IF(H143="","",IF(TODAY()>H143,"Atrasado (em aberto)","Em aberto")),IF(I143<=H143,"No prazo","Fora do prazo")))
A144: PV1143 | B144: 45823 | C144: C013 | D144: Produto A 1kg | E144: 4.5 | F144: 48627.91 | G144: CIF | H144: 45853 | I144: 45847 | J144: =IF(C144="","",IFERROR(INDEX(Clientes!$B:$B,MATCH(C144,Clientes!$A:$A,0)),"Cód. não cadastrado")) | K144: =IF(B144="","",YEAR(B144)) | L144: =IF(B144="","",MONTH(B144)) | M144: =IF(OR(B144="",I144=""),"",I144-B144) | N144: =IF(B144="","",IF(I144="",IF(H144="","",IF(TODAY()>H144,"Atrasado (em aberto)","Em aberto")),IF(I144<=H144,"No prazo","Fora do prazo")))
A145: PV1144 | B145: 45880 | C145: C013 | D145: Produto B 5kg | E145: 5 | F145: 57919.31 | G145: FOB | H145: 45910 | I145: 45910 | J145: =IF(C145="","",IFERROR(INDEX(Clientes!$B:$B,MATCH(C145,Clientes!$A:$A,0)),"Cód. não cadastrado")) | K145: =IF(B145="","",YEAR(B145)) | L145: =IF(B145="","",MONTH(B145)) | M145: =IF(OR(B145="",I145=""),"",I145-B145) | N145: =IF(B145="","",IF(I145="",IF(H145="","",IF(TODAY()>H145,"Atrasado (em aberto)","Em aberto")),IF(I145<=H145,"No prazo","Fora do prazo")))
A146: PV1145 | B146: 45939 | C146: C013 | D146: Produto C granel 25kg | E146: 7.1 | F146: 56590.26 | G146: CFR | H146: 45969 | I146: 45974 | J146: =IF(C146="","",IFERROR(INDEX(Clientes!$B:$B,MATCH(C146,Clientes!$A:$A,0)),"Cód. não cadastrado")) | K146: =IF(B146="","",YEAR(B146)) | L146: =IF(B146="","",MONTH(B146)) | M146: =IF(OR(B146="",I146=""),"",I146-B146) | N146: =IF(B146="","",IF(I146="",IF(H146="","",IF(TODAY()>H146,"Atrasado (em aberto)","Em aberto")),IF(I146<=H146,"No prazo","Fora do prazo")))
A147: PV1146 | B147: 45992 | C147: C013 | D147: Produto C granel 25kg | E147: 8.5 | F147: 43529.1 | G147: FOB | H147: 46022 | I147: 46027 | J147: =IF(C147="","",IFERROR(INDEX(Clientes!$B:$B,MATCH(C147,Clientes!$A:$A,0)),"Cód. não cadastrado")) | K147: =IF(B147="","",YEAR(B147)) | L147: =IF(B147="","",MONTH(B147)) | M147: =IF(OR(B147="",I147=""),"",I147-B147) | N147: =IF(B147="","",IF(I147="",IF(H147="","",IF(TODAY()>H147,"Atrasado (em aberto)","Em aberto")),IF(I147<=H147,"No prazo","Fora do prazo")))
A148: PV1147 | B148: 46026 | C148: C013 | D148: Produto C granel 25kg | E148: 8.7 | F148: 57925.98 | G148: CFR | H148: 46056 | I148: 46056 | J148: =IF(C148="","",IFERROR(INDEX(Clientes!$B:$B,MATCH(C148,Clientes!$A:$A,0)),"Cód. não cadastrado")) | K148: =IF(B148="","",YEAR(B148)) | L148: =IF(B148="","",MONTH(B148)) | M148: =IF(OR(B148="",I148=""),"",I148-B148) | N148: =IF(B148="","",IF(I148="",IF(H148="","",IF(TODAY()>H148,"Atrasado (em aberto)","Em aberto")),IF(I148<=H148,"No prazo","Fora do prazo")))
A149: PV1148 | B149: 46095 | C149: C013 | D149: Produto B 5kg | E149: 3.8 | F149: 37344.33 | G149: FOB | H149: 46125 | I149: 46134 | J149: =IF(C149="","",IFERROR(INDEX(Clientes!$B:$B,MATCH(C149,Clientes!$A:$A,0)),"Cód. não cadastrado")) | K149: =IF(B149="","",YEAR(B149)) | L149: =IF(B149="","",MONTH(B149)) | M149: =IF(OR(B149="",I149=""),"",I149-B149) | N149: =IF(B149="","",IF(I149="",IF(H149="","",IF(TODAY()>H149,"Atrasado (em aberto)","Em aberto")),IF(I149<=H149,"No prazo","Fora do prazo")))
A150: PV1149 | B150: 46166 | C150: C013 | D150: Produto C granel 25kg | E150: 7.6 | F150: 42326.44 | G150: CFR | H150: 46196 | I150: 46196 | J150: =IF(C150="","",IFERROR(INDEX(Clientes!$B:$B,MATCH(C150,Clientes!$A:$A,0)),"Cód. não cadastrado")) | K150: =IF(B150="","",YEAR(B150)) | L150: =IF(B150="","",MONTH(B150)) | M150: =IF(OR(B150="",I150=""),"",I150-B150) | N150: =IF(B150="","",IF(I150="",IF(H150="","",IF(TODAY()>H150,"Atrasado (em aberto)","Em aberto")),IF(I150<=H150,"No prazo","Fora do prazo")))
A151: PV1150 | B151: 46218 | C151: C013 | D151: Produto C granel 25kg | E151: 3.5 | F151: 23879.03 | G151: FOB | H151: 46248 | I151: 46248 | J151: =IF(C151="","",IFERROR(INDEX(Clientes!$B:$B,MATCH(C151,Clientes!$A:$A,0)),"Cód. não cadastrado")) | K151: =IF(B151="","",YEAR(B151)) | L151: =IF(B151="","",MONTH(B151)) | M151: =IF(OR(B151="",I151=""),"",I151-B151) | N151: =IF(B151="","",IF(I151="",IF(H151="","",IF(TODAY()>H151,"Atrasado (em aberto)","Em aberto")),IF(I151<=H151,"No prazo","Fora do prazo")))
A152: PV1151 | B152: 46268 | C152: C013 | D152: Produto A 1kg | E152: 5.9 | F152: 39507.75 | G152: FOB | H152: 46298 | J152: =IF(C152="","",IFERROR(INDEX(Clientes!$B:$B,MATCH(C152,Clientes!$A:$A,0)),"Cód. não cadastrado")) | K152: =IF(B152="","",YEAR(B152)) | L152: =IF(B152="","",MONTH(B152)) | M152: =IF(OR(B152="",I152=""),"",I152-B152) | N152: =IF(B152="","",IF(I152="",IF(H152="","",IF(TODAY()>H152,"Atrasado (em aberto)","Em aberto")),IF(I152<=H152,"No prazo","Fora do prazo")))
A153: PV1152 | B153: 45692 | C153: C014 | D153: Produto B 5kg | E153: 6.7 | F153: 24375.35 | G153: CFR | H153: 45722 | I153: 45716 | J153: =IF(C153="","",IFERROR(INDEX(Clientes!$B:$B,MATCH(C153,Clientes!$A:$A,0)),"Cód. não cadastrado")) | K153: =IF(B153="","",YEAR(B153)) | L153: =IF(B153="","",MONTH(B153)) | M153: =IF(OR(B153="",I153=""),"",I153-B153) | N153: =IF(B153="","",IF(I153="",IF(H153="","",IF(TODAY()>H153,"Atrasado (em aberto)","Em aberto")),IF(I153<=H153,"No prazo","Fora do prazo")))
A154: PV1153 | B154: 45793 | C154: C014 | D154: Produto B 5kg | E154: 4 | F154: 20981.9 | G154: CFR | H154: 45823 | I154: 45828 | J154: =IF(C154="","",IFERROR(INDEX(Clientes!$B:$B,MATCH(C154,Clientes!$A:$A,0)),"Cód. não cadastrado")) | K154: =IF(B154="","",YEAR(B154)) | L154: =IF(B154="","",MONTH(B154)) | M154: =IF(OR(B154="",I154=""),"",I154-B154) | N154: =IF(B154="","",IF(I154="",IF(H154="","",IF(TODAY()>H154,"Atrasado (em aberto)","Em aberto")),IF(I154<=H154,"No prazo","Fora do prazo")))
A155: PV1154 | B155: 45889 | C155: C014 | D155: Produto A 1kg | E155: 7.5 | F155: 53114.42 | G155: CIF | H155: 45919 | I155: 45924 | J155: =IF(C155="","",IFERROR(INDEX(Clientes!$B:$B,MATCH(C155,Clientes!$A:$A,0)),"Cód. não cadastrado")) | K155: =IF(B155="","",YEAR(B155)) | L155: =IF(B155="","",MONTH(B155)) | M155: =IF(OR(B155="",I155=""),"",I155-B155) | N155: =IF(B155="","",IF(I155="",IF(H155="","",IF(TODAY()>H155,"Atrasado (em aberto)","Em aberto")),IF(I155<=H155,"No prazo","Fora do prazo")))
A156: PV1155 | B156: 45986 | C156: C014 | D156: Produto B 5kg | E156: 4.8 | F156: 40509.79 | G156: CFR | H156: 46016 | I156: 46010 | J156: =IF(C156="","",IFERROR(INDEX(Clientes!$B:$B,MATCH(C156,Clientes!$A:$A,0)),"Cód. não cadastrado")) | K156: =IF(B156="","",YEAR(B156)) | L156: =IF(B156="","",MONTH(B156)) | M156: =IF(OR(B156="",I156=""),"",I156-B156) | N156: =IF(B156="","",IF(I156="",IF(H156="","",IF(TODAY()>H156,"Atrasado (em aberto)","Em aberto")),IF(I156<=H156,"No prazo","Fora do prazo")))
A157: PV1156 | B157: 46060 | C157: C014 | D157: Produto A 1kg | E157: 4.1 | F157: 25597.68 | G157: CFR | H157: 46090 | I157: 46090 | J157: =IF(C157="","",IFERROR(INDEX(Clientes!$B:$B,MATCH(C157,Clientes!$A:$A,0)),"Cód. não cadastrado")) | K157: =IF(B157="","",YEAR(B157)) | L157: =IF(B157="","",MONTH(B157)) | M157: =IF(OR(B157="",I157=""),"",I157-B157) | N157: =IF(B157="","",IF(I157="",IF(H157="","",IF(TODAY()>H157,"Atrasado (em aberto)","Em aberto")),IF(I157<=H157,"No prazo","Fora do prazo")))
A158: PV1157 | B158: 46161 | C158: C014 | D158: Produto B 5kg | E158: 3.4 | F158: 26324.42 | G158: FOB | H158: 46191 | I158: 46188 | J158: =IF(C158="","",IFERROR(INDEX(Clientes!$B:$B,MATCH(C158,Clientes!$A:$A,0)),"Cód. não cadastrado")) | K158: =IF(B158="","",YEAR(B158)) | L158: =IF(B158="","",MONTH(B158)) | M158: =IF(OR(B158="",I158=""),"",I158-B158) | N158: =IF(B158="","",IF(I158="",IF(H158="","",IF(TODAY()>H158,"Atrasado (em aberto)","Em aberto")),IF(I158<=H158,"No prazo","Fora do prazo")))
A159: PV1158 | B159: 46242 | C159: C014 | D159: Produto A 1kg | E159: 6.9 | F159: 59593 | G159: FOB | H159: 46272 | I159: 46277 | J159: =IF(C159="","",IFERROR(INDEX(Clientes!$B:$B,MATCH(C159,Clientes!$A:$A,0)),"Cód. não cadastrado")) | K159: =IF(B159="","",YEAR(B159)) | L159: =IF(B159="","",MONTH(B159)) | M159: =IF(OR(B159="",I159=""),"",I159-B159) | N159: =IF(B159="","",IF(I159="",IF(H159="","",IF(TODAY()>H159,"Atrasado (em aberto)","Em aberto")),IF(I159<=H159,"No prazo","Fora do prazo")))
A160: PV1159 | B160: 45673 | C160: C015 | D160: Produto A 1kg | E160: 8 | F160: 56146.9 | G160: FOB | H160: 45703 | I160: 45712 | J160: =IF(C160="","",IFERROR(INDEX(Clientes!$B:$B,MATCH(C160,Clientes!$A:$A,0)),"Cód. não cadastrado")) | K160: =IF(B160="","",YEAR(B160)) | L160: =IF(B160="","",MONTH(B160)) | M160: =IF(OR(B160="",I160=""),"",I160-B160) | N160: =IF(B160="","",IF(I160="",IF(H160="","",IF(TODAY()>H160,"Atrasado (em aberto)","Em aberto")),IF(I160<=H160,"No prazo","Fora do prazo")))
A161: PV1160 | B161: 45726 | C161: C015 | D161: Produto A 1kg | E161: 3.3 | F161: 42022.2 | G161: CIF | H161: 45756 | I161: 45753 | J161: =IF(C161="","",IFERROR(INDEX(Clientes!$B:$B,MATCH(C161,Clientes!$A:$A,0)),"Cód. não cadastrado")) | K161: =IF(B161="","",YEAR(B161)) | L161: =IF(B161="","",MONTH(B161)) | M161: =IF(OR(B161="",I161=""),"",I161-B161) | N161: =IF(B161="","",IF(I161="",IF(H161="","",IF(TODAY()>H161,"Atrasado (em aberto)","Em aberto")),IF(I161<=H161,"No prazo","Fora do prazo")))
A162: PV1161 | B162: 45784 | C162: C015 | D162: Produto B 5kg | E162: 6.1 | F162: 22999.16 | G162: CIF | H162: 45814 | I162: 45808 | J162: =IF(C162="","",IFERROR(INDEX(Clientes!$B:$B,MATCH(C162,Clientes!$A:$A,0)),"Cód. não cadastrado")) | K162: =IF(B162="","",YEAR(B162)) | L162: =IF(B162="","",MONTH(B162)) | M162: =IF(OR(B162="",I162=""),"",I162-B162) | N162: =IF(B162="","",IF(I162="",IF(H162="","",IF(TODAY()>H162,"Atrasado (em aberto)","Em aberto")),IF(I162<=H162,"No prazo","Fora do prazo")))
A163: PV1162 | B163: 45847 | C163: C015 | D163: Produto C granel 25kg | E163: 8.7 | F163: 19760.1 | G163: CIF | H163: 45877 | I163: 45886 | J163: =IF(C163="","",IFERROR(INDEX(Clientes!$B:$B,MATCH(C163,Clientes!$A:$A,0)),"Cód. não cadastrado")) | K163: =IF(B163="","",YEAR(B163)) | L163: =IF(B163="","",MONTH(B163)) | M163: =IF(OR(B163="",I163=""),"",I163-B163) | N163: =IF(B163="","",IF(I163="",IF(H163="","",IF(TODAY()>H163,"Atrasado (em aberto)","Em aberto")),IF(I163<=H163,"No prazo","Fora do prazo")))
A164: PV1163 | B164: 45923 | C164: C015 | D164: Produto B 5kg | E164: 4.3 | F164: 31591.88 | G164: FOB | H164: 45953 | I164: 45955 | J164: =IF(C164="","",IFERROR(INDEX(Clientes!$B:$B,MATCH(C164,Clientes!$A:$A,0)),"Cód. não cadastrado")) | K164: =IF(B164="","",YEAR(B164)) | L164: =IF(B164="","",MONTH(B164)) | M164: =IF(OR(B164="",I164=""),"",I164-B164) | N164: =IF(B164="","",IF(I164="",IF(H164="","",IF(TODAY()>H164,"Atrasado (em aberto)","Em aberto")),IF(I164<=H164,"No prazo","Fora do prazo")))
... A167: PV1166 | B167: 46158 | C167: C015 | D167: Produto B 5kg | E167: 3.6 | F167: 32788.35 | G167: CIF | H167: 46188 | I167: 46182 | J167: =IF(C167="","",IFERROR(INDEX(Clientes!$B:$B,MATCH(C167,Clientes!$A:$A,0)),"Cód. não cadastrado")) | K167: =IF(B167="","",YEAR(B167)) | L167: =IF(B167="","",MONTH(B167)) | M167: =IF(OR(B167="",I167=""),"",I167-B167) | N167: =IF(B167="","",IF(I167="",IF(H167="","",IF(TODAY()>H167,"Atrasado (em aberto)","Em aberto")),IF(I167<=H167,"No prazo","Fora do prazo")))
A168: PV1167 | B168: 46286 | C168: C015 | D168: Produto B 5kg | E168: 7.2 | F168: 33440.5 | G168: CFR | H168: 46316 | J168: =IF(C168="","",IFERROR(INDEX(Clientes!$B:$B,MATCH(C168,Clientes!$A:$A,0)),"Cód. não cadastrado")) | K168: =IF(B168="","",YEAR(B168)) | L168: =IF(B168="","",MONTH(B168)) | M168: =IF(OR(B168="",I168=""),"",I168-B168) | N168: =IF(B168="","",IF(I168="",IF(H168="","",IF(TODAY()>H168,"Atrasado (em aberto)","Em aberto")),IF(I168<=H168,"No prazo","Fora do prazo")))
A169: PV1168 | B169: 45671 | C169: C016 | D169: Produto B 5kg | E169: 7.5 | F169: 54766.27 | G169: CFR | H169: 45701 | I169: 45695 | J169: =IF(C169="","",IFERROR(INDEX(Clientes!$B:$B,MATCH(C169,Clientes!$A:$A,0)),"Cód. não cadastrado")) | K169: =IF(B169="","",YEAR(B169)) | L169: =IF(B169="","",MONTH(B169)) | M169: =IF(OR(B169="",I169=""),"",I169-B169) | N169: =IF(B169="","",IF(I169="",IF(H169="","",IF(TODAY()>H169,"Atrasado (em aberto)","Em aberto")),IF(I169<=H169,"No prazo","Fora do prazo")))
A170: PV1169 | B170: 45702 | C170: C016 | D170: Produto B 5kg | E170: 6.9 | F170: 32582.9 | G170: CFR | H170: 45732 | I170: 45726 | J170: =IF(C170="","",IFERROR(INDEX(Clientes!$B:$B,MATCH(C170,Clientes!$A:$A,0)),"Cód. não cadastrado")) | K170: =IF(B170="","",YEAR(B170)) | L170: =IF(B170="","",MONTH(B170)) | M170: =IF(OR(B170="",I170=""),"",I170-B170) | N170: =IF(B170="","",IF(I170="",IF(H170="","",IF(TODAY()>H170,"Atrasado (em aberto)","Em aberto")),IF(I170<=H170,"No prazo","Fora do prazo")))
A171: PV1170 | B171: 45723 | C171: C016 | D171: Produto B 5kg | E171: 8.4 | F171: 34068.97 | G171: FOB | H171: 45753 | I171: 45747 | J171: =IF(C171="","",IFERROR(INDEX(Clientes!$B:$B,MATCH(C171,Clientes!$A:$A,0)),"Cód. não cadastrado")) | K171: =IF(B171="","",YEAR(B171)) | L171: =IF(B171="","",MONTH(B171)) | M171: =IF(OR(B171="",I171=""),"",I171-B171) | N171: =IF(B171="","",IF(I171="",IF(H171="","",IF(TODAY()>H171,"Atrasado (em aberto)","Em aberto")),IF(I171<=H171,"No prazo","Fora do prazo")))
A172: PV1171 | B172: 45760 | C172: C016 | D172: Produto B 5kg | E172: 5.8 | F172: 22314.51 | G172: FOB | H172: 45790 | I172: 45792 | J172: =IF(C172="","",IFERROR(INDEX(Clientes!$B:$B,MATCH(C172,Clientes!$A:$A,0)),"Cód. não cadastrado")) | K172: =IF(B172="","",YEAR(B172)) | L172: =IF(B172="","",MONTH(B172)) | M172: =IF(OR(B172="",I172=""),"",I172-B172) | N172: =IF(B172="","",IF(I172="",IF(H172="","",IF(TODAY()>H172,"Atrasado (em aberto)","Em aberto")),IF(I172<=H172,"No prazo","Fora do prazo")))
A173: PV1172 | B173: 45779 | C173: C016 | D173: Produto A 1kg | E173: 6.8 | F173: 55940.75 | G173: FOB | H173: 45809 | I173: 45811 | J173: =IF(C173="","",IFERROR(INDEX(Clientes!$B:$B,MATCH(C173,Clientes!$A:$A,0)),"Cód. não cadastrado")) | K173: =IF(B173="","",YEAR(B173)) | L173: =IF(B173="","",MONTH(B173)) | M173: =IF(OR(B173="",I173=""),"",I173-B173) | N173: =IF(B173="","",IF(I173="",IF(H173="","",IF(TODAY()>H173,"Atrasado (em aberto)","Em aberto")),IF(I173<=H173,"No prazo","Fora do prazo")))
A174: PV1173 | B174: 45827 | C174: C016 | D174: Produto B 5kg | E174: 7.4 | F174: 22725.85 | G174: CFR | H174: 45857 | I174: 45859 | J174: =IF(C174="","",IFERROR(INDEX(Clientes!$B:$B,MATCH(C174,Clientes!$A:$A,0)),"Cód. não cadastrado")) | K174: =IF(B174="","",YEAR(B174)) | L174: =IF(B174="","",MONTH(B174)) | M174: =IF(OR(B174="",I174=""),"",I174-B174) | N174: =IF(B174="","",IF(I174="",IF(H174="","",IF(TODAY()>H174,"Atrasado (em aberto)","Em aberto")),IF(I174<=H174,"No prazo","Fora do prazo")))
A175: PV1174 | B175: 45848 | C175: C016 | D175: Produto C granel 25kg | E175: 4 | F175: 18019.35 | G175: CFR | H175: 45878 | I175: 45875 | J175: =IF(C175="","",IFERROR(INDEX(Clientes!$B:$B,MATCH(C175,Clientes!$A:$A,0)),"Cód. não cadastrado")) | K175: =IF(B175="","",YEAR(B175)) | L175: =IF(B175="","",MONTH(B175)) | M175: =IF(OR(B175="",I175=""),"",I175-B175) | N175: =IF(B175="","",IF(I175="",IF(H175="","",IF(TODAY()>H175,"Atrasado (em aberto)","Em aberto")),IF(I175<=H175,"No prazo","Fora do prazo")))
A176: PV1175 | B176: 45885 | C176: C016 | D176: Produto A 1kg | E176: 4.8 | F176: 52678.15 | G176: FOB | H176: 45915 | I176: 45924 | J176: =IF(C176="","",IFERROR(INDEX(Clientes!$B:$B,MATCH(C176,Clientes!$A:$A,0)),"Cód. não cadastrado")) | K176: =IF(B176="","",YEAR(B176)) | L176: =IF(B176="","",MONTH(B176)) | M176: =IF(OR(B176="",I176=""),"",I176-B176) | N176: =IF(B176="","",IF(I176="",IF(H176="","",IF(TODAY()>H176,"Atrasado (em aberto)","Em aberto")),IF(I176<=H176,"No prazo","Fora do prazo")))
A177: PV1176 | B177: 45916 | C177: C016 | D177: Produto A 1kg | E177: 6.6 | F177: 43636.55 | G177: FOB | H177: 45946 | I177: 45946 | J177: =IF(C177="","",IFERROR(INDEX(Clientes!$B:$B,MATCH(C177,Clientes!$A:$A,0)),"Cód. não cadastrado")) | K177: =IF(B177="","",YEAR(B177)) | L177: =IF(B177="","",MONTH(B177)) | M177: =IF(OR(B177="",I177=""),"",I177-B177) | N177: =IF(B177="","",IF(I177="",IF(H177="","",IF(TODAY()>H177,"Atrasado (em aberto)","Em aberto")),IF(I177<=H177,"No prazo","Fora do prazo")))
A178: PV1177 | B178: 45953 | C178: C016 | D178: Produto C granel 25kg | E178: 7.9 | F178: 22212.43 | G178: FOB | H178: 45983 | I178: 45985 | J178: =IF(C178="","",IFERROR(INDEX(Clientes!$B:$B,MATCH(C178,Clientes!$A:$A,0)),"Cód. não cadastrado")) | K178: =IF(B178="","",YEAR(B178)) | L178: =IF(B178="","",MONTH(B178)) | M178: =IF(OR(B178="",I178=""),"",I178-B178) | N178: =IF(B178="","",IF(I178="",IF(H178="","",IF(TODAY()>H178,"Atrasado (em aberto)","Em aberto")),IF(I178<=H178,"No prazo","Fora do prazo")))
A179: PV1178 | B179: 45981 | C179: C016 | D179: Produto C granel 25kg | E179: 8.1 | F179: 52313.45 | G179: FOB | H179: 46011 | I179: 46011 | J179: =IF(C179="","",IFERROR(INDEX(Clientes!$B:$B,MATCH(C179,Clientes!$A:$A,0)),"Cód. não cadastrado")) | K179: =IF(B179="","",YEAR(B179)) | L179: =IF(B179="","",MONTH(B179)) | M179: =IF(OR(B179="",I179=""),"",I179-B179) | N179: =IF(B179="","",IF(I179="",IF(H179="","",IF(TODAY()>H179,"Atrasado (em aberto)","Em aberto")),IF(I179<=H179,"No prazo","Fora do prazo")))
A180: PV1179 | B180: 46010 | C180: C016 | D180: Produto A 1kg | E180: 5.4 | F180: 38305.16 | G180: CFR | H180: 46040 | I180: 46037 | J180: =IF(C180="","",IFERROR(INDEX(Clientes!$B:$B,MATCH(C180,Clientes!$A:$A,0)),"Cód. não cadastrado")) | K180: =IF(B180="","",YEAR(B180)) | L180: =IF(B180="","",MONTH(B180)) | M180: =IF(OR(B180="",I180=""),"",I180-B180) | N180: =IF(B180="","",IF(I180="",IF(H180="","",IF(TODAY()>H180,"Atrasado (em aberto)","Em aberto")),IF(I180<=H180,"No prazo","Fora do prazo")))
... A206: PV1205 | B206: 46260 | C206: C018 | D206: Produto B 5kg | E206: 7.9 | F206: 58521.09 | G206: FOB | H206: 46290 | I206: 46290 | J206: =IF(C206="","",IFERROR(INDEX(Clientes!$B:$B,MATCH(C206,Clientes!$A:$A,0)),"Cód. não cadastrado")) | K206: =IF(B206="","",YEAR(B206)) | L206: =IF(B206="","",MONTH(B206)) | M206: =IF(OR(B206="",I206=""),"",I206-B206) | N206: =IF(B206="","",IF(I206="",IF(H206="","",IF(TODAY()>H206,"Atrasado (em aberto)","Em aberto")),IF(I206<=H206,"No prazo","Fora do prazo")))
A207: PV1206 | B207: 46283 | C207: C018 | D207: Produto C granel 25kg | E207: 6.9 | F207: 34968.94 | G207: CIF | H207: 46313 | J207: =IF(C207="","",IFERROR(INDEX(Clientes!$B:$B,MATCH(C207,Clientes!$A:$A,0)),"Cód. não cadastrado")) | K207: =IF(B207="","",YEAR(B207)) | L207: =IF(B207="","",MONTH(B207)) | M207: =IF(OR(B207="",I207=""),"",I207-B207) | N207: =IF(B207="","",IF(I207="",IF(H207="","",IF(TODAY()>H207,"Atrasado (em aberto)","Em aberto")),IF(I207<=H207,"No prazo","Fora do prazo")))
A208: PV1207 | B208: 45732 | C208: C019 | D208: Produto A 1kg | E208: 8.4 | F208: 16980.09 | G208: CIF | H208: 45762 | I208: 45759 | J208: =IF(C208="","",IFERROR(INDEX(Clientes!$B:$B,MATCH(C208,Clientes!$A:$A,0)),"Cód. não cadastrado")) | K208: =IF(B208="","",YEAR(B208)) | L208: =IF(B208="","",MONTH(B208)) | M208: =IF(OR(B208="",I208=""),"",I208-B208) | N208: =IF(B208="","",IF(I208="",IF(H208="","",IF(TODAY()>H208,"Atrasado (em aberto)","Em aberto")),IF(I208<=H208,"No prazo","Fora do prazo")))
A209: PV1208 | B209: 45809 | C209: C019 | D209: Produto A 1kg | E209: 4.4 | F209: 17627.06 | G209: FOB | H209: 45839 | I209: 45839 | J209: =IF(C209="","",IFERROR(INDEX(Clientes!$B:$B,MATCH(C209,Clientes!$A:$A,0)),"Cód. não cadastrado")) | K209: =IF(B209="","",YEAR(B209)) | L209: =IF(B209="","",MONTH(B209)) | M209: =IF(OR(B209="",I209=""),"",I209-B209) | N209: =IF(B209="","",IF(I209="",IF(H209="","",IF(TODAY()>H209,"Atrasado (em aberto)","Em aberto")),IF(I209<=H209,"No prazo","Fora do prazo")))
A210: PV1209 | B210: 45901 | C210: C019 | D210: Produto C granel 25kg | E210: 6.9 | F210: 23876.62 | G210: CFR | H210: 45931 | I210: 45933 | J210: =IF(C210="","",IFERROR(INDEX(Clientes!$B:$B,MATCH(C210,Clientes!$A:$A,0)),"Cód. não cadastrado")) | K210: =IF(B210="","",YEAR(B210)) | L210: =IF(B210="","",MONTH(B210)) | M210: =IF(OR(B210="",I210=""),"",I210-B210) | N210: =IF(B210="","",IF(I210="",IF(H210="","",IF(TODAY()>H210,"Atrasado (em aberto)","Em aberto")),IF(I210<=H210,"No prazo","Fora do prazo")))
...

Sheet Acompanhamento
A1: Mês ref. | B1: Cód. Cliente | C1: Cliente | D1: Compra prevista em | E1: Situação | F1: Motivo | G1: Detalhe do motivo | H1: Ação combinada | I1: Responsável | J1: Data de retorno | K1: Status da ação | L1: Chance de recompra

Sheet S_Atividades
A1: Nº Pedido | B1: Cliente | C1: Departamento | D1: Atividade | E1: Data solicitação | F1: Prazo (dias) | G1: Data conclusão | H1: Nº cobranças | I1: Última cobrança | J1: Causa do atraso | K1: Observação | L1: Data limite | M1: Status | N1: Dias de atraso
A2: PV1239 | B2: Cliente Exemplo 26 | C2: Marketing/Arte | D2: Arte de rótulo no idioma | E2: 46282 | G2: 46291 | H2: 1 | I2: 46289 | J2: Aguardando aprovação do cliente | L2: =IF(E2="","",E2+IF(F2="",IFERROR(VLOOKUP(C2,Parametros!$E:$F,2,0),0),F2)) | M2: =IF(E2="","",IF(G2="",IF(TODAY()>L2,"Atrasada","Em aberto"),IF(G2<=L2,"No prazo","Com atraso"))) | N2: =IF(E2="","",MAX(0,IF(G2="",TODAY(),G2)-L2))
A3: PV1239 | B3: Cliente Exemplo 26 | C3: PCP/Produção | D3: Programar produção | E3: 46283 | H3: 3 | I3: 46298 | J3: Fila da produção | L3: =IF(E3="","",E3+IF(F3="",IFERROR(VLOOKUP(C3,Parametros!$E:$F,2,0),0),F3)) | M3: =IF(E3="","",IF(G3="",IF(TODAY()>L3,"Atrasada","Em aberto"),IF(G3<=L3,"No prazo","Com atraso"))) | N3: =IF(E3="","",MAX(0,IF(G3="",TODAY(),G3)-L3))
A4: PV1239 | B4: Cliente Exemplo 26 | C4: Financeiro | D4: Liberação de crédito / carta de crédito | E4: 46281 | G4: 46284 | H4: 2 | I4: 46284 | L4: =IF(E4="","",E4+IF(F4="",IFERROR(VLOOKUP(C4,Parametros!$E:$F,2,0),0),F4)) | M4: =IF(E4="","",IF(G4="",IF(TODAY()>L4,"Atrasada","Em aberto"),IF(G4<=L4,"No prazo","Com atraso"))) | N4: =IF(E4="","",MAX(0,IF(G4="",TODAY(),G4)-L4))
A5: PV1239 | B5: Cliente Exemplo 26 | C5: Logística/Embarque | D5: Booking e coleta do contêiner | E5: 46282 | G5: 46289 | H5: 1 | I5: 46287 | J5: Aguardando aprovação do cliente | L5: =IF(E5="","",E5+IF(F5="",IFERROR(VLOOKUP(C5,Parametros!$E:$F,2,0),0),F5)) | M5: =IF(E5="","",IF(G5="",IF(TODAY()>L5,"Atrasada","Em aberto"),IF(G5<=L5,"No prazo","Com atraso"))) | N5: =IF(E5="","",MAX(0,IF(G5="",TODAY(),G5)-L5))
A6: PV1239 | B6: Cliente Exemplo 26 | C6: Comercial/Comex | D6: Proforma e confirmação | E6: 46282 | G6: 46284 | H6: 1 | I6: 46284 | L6: =IF(E6="","",E6+IF(F6="",IFERROR(VLOOKUP(C6,Parametros!$E:$F,2,0),0),F6)) | M6: =IF(E6="","",IF(G6="",IF(TODAY()>L6,"Atrasada","Em aberto"),IF(G6<=L6,"No prazo","Com atraso"))) | N6: =IF(E6="","",MAX(0,IF(G6="",TODAY(),G6)-L6))
A7: PV1238 | B7: Cliente Exemplo 25 | C7: Qualidade/Regulatório | D7: Certificado sanitário / análise | E7: 46283 | G7: 46289 | H7: 1 | I7: 46290 | L7: =IF(E7="","",E7+IF(F7="",IFERROR(VLOOKUP(C7,Parametros!$E:$F,2,0),0),F7)) | M7: =IF(E7="","",IF(G7="",IF(TODAY()>L7,"Atrasada","Em aberto"),IF(G7<=L7,"No prazo","Com atraso"))) | N7: =IF(E7="","",MAX(0,IF(G7="",TODAY(),G7)-L7))
A8: PV1238 | B8: Cliente Exemplo 25 | C8: Marketing/Arte | D8: Arte de rótulo no idioma | E8: 46284 | G8: 46290 | H8: 1 | I8: 46291 | L8: =IF(E8="","",E8+IF(F8="",IFERROR(VLOOKUP(C8,Parametros!$E:$F,2,0),0),F8)) | M8: =IF(E8="","",IF(G8="",IF(TODAY()>L8,"Atrasada","Em aberto"),IF(G8<=L8,"No prazo","Com atraso"))) | N8: =IF(E8="","",MAX(0,IF(G8="",TODAY(),G8)-L8))
A9: PV1238 | B9: Cliente Exemplo 25 | C9: Financeiro | D9: Liberação de crédito / carta de crédito | E9: 46284 | G9: 46286 | H9: 1 | I9: 46287 | L9: =IF(E9="","",E9+IF(F9="",IFERROR(VLOOKUP(C9,Parametros!$E:$F,2,0),0),F9)) | M9: =IF(E9="","",IF(G9="",IF(TODAY()>L9,"Atrasada","Em aberto"),IF(G9<=L9,"No prazo","Com atraso"))) | N9: =IF(E9="","",MAX(0,IF(G9="",TODAY(),G9)-L9))
A10: PV1238 | B10: Cliente Exemplo 25 | C10: PCP/Produção | D10: Programar produção | E10: 46282 | G10: 46296 | H10: 0 | L10: =IF(E10="","",E10+IF(F10="",IFERROR(VLOOKUP(C10,Parametros!$E:$F,2,0),0),F10)) | M10: =IF(E10="","",IF(G10="",IF(TODAY()>L10,"Atrasada","Em aberto"),IF(G10<=L10,"No prazo","Com atraso"))) | N10: =IF(E10="","",MAX(0,IF(G10="",TODAY(),G10)-L10))
A11: PV1238 | B11: Cliente Exemplo 25 | C11: Compras/Suprimentos | D11: Compra de embalagem/insumos | E11: 46283 | G11: 46293 | H11: 1 | I11: 46293 | L11: =IF(E11="","",E11+IF(F11="",IFERROR(VLOOKUP(C11,Parametros!$E:$F,2,0),0),F11)) | M11: =IF(E11="","",IF(G11="",IF(TODAY()>L11,"Atrasada","Em aberto"),IF(G11<=L11,"No prazo","Com atraso"))) | N11: =IF(E11="","",MAX(0,IF(G11="",TODAY(),G11)-L11))
A12: PV1237 | B12: Cliente Exemplo 24 | C12: PCP/Produção | D12: Programar produção | E12: 46271 | G12: 46283 | H12: 0 | L12: =IF(E12="","",E12+IF(F12="",IFERROR(VLOOKUP(C12,Parametros!$E:$F,2,0),0),F12)) | M12: =IF(E12="","",IF(G12="",IF(TODAY()>L12,"Atrasada","Em aberto"),IF(G12<=L12,"No prazo","Com atraso"))) | N12: =IF(E12="","",MAX(0,IF(G12="",TODAY(),G12)-L12))
A13: PV1237 | B13: Cliente Exemplo 24 | C13: Logística/Embarque | D13: Booking e coleta do contêiner | E13: 46272 | G13: 46276 | H13: 2 | I13: 46277 | L13: =IF(E13="","",E13+IF(F13="",IFERROR(VLOOKUP(C13,Parametros!$E:$F,2,0),0),F13)) | M13: =IF(E13="","",IF(G13="",IF(TODAY()>L13,"Atrasada","Em aberto"),IF(G13<=L13,"No prazo","Com atraso"))) | N13: =IF(E13="","",MAX(0,IF(G13="",TODAY(),G13)-L13))
A14: PV1237 | B14: Cliente Exemplo 24 | C14: Marketing/Arte | D14: Arte de rótulo no idioma | E14: 46273 | G14: 46277 | H14: 0 | L14: =IF(E14="","",E14+IF(F14="",IFERROR(VLOOKUP(C14,Parametros!$E:$F,2,0),0),F14)) | M14: =IF(E14="","",IF(G14="",IF(TODAY()>L14,"Atrasada","Em aberto"),IF(G14<=L14,"No prazo","Com atraso"))) | N14: =IF(E14="","",MAX(0,IF(G14="",TODAY(),G14)-L14))
A15: PV1237 | B15: Cliente Exemplo 24 | C15: Qualidade/Regulatório | D15: Certificado sanitário / análise | E15: 46273 | G15: 46288 | H15: 2 | I15: 46280 | J15: Aguardando aprovação do cliente | L15: =IF(E15="","",E15+IF(F15="",IFERROR(VLOOKUP(C15,Parametros!$E:$F,2,0),0),F15)) | M15: =IF(E15="","",IF(G15="",IF(TODAY()>L15,"Atrasada","Em aberto"),IF(G15<=L15,"No prazo","Com atraso"))) | N15: =IF(E15="","",MAX(0,IF(G15="",TODAY(),G15)-L15))
A16: PV1237 | B16: Cliente Exemplo 24 | C16: Financeiro | D16: Liberação de crédito / carta de crédito | E16: 46272 | G16: 46275 | H16: 0 | L16: =IF(E16="","",E16+IF(F16="",IFERROR(VLOOKUP(C16,Parametros!$E:$F,2,0),0),F16)) | M16: =IF(E16="","",IF(G16="",IF(TODAY()>L16,"Atrasada","Em aberto"),IF(G16<=L16,"No prazo","Com atraso"))) | N16: =IF(E16="","",MAX(0,IF(G16="",TODAY(),G16)-L16))
A17: PV1236 | B17: Cliente Exemplo 23 | C17: PCP/Produção | D17: Programar produção | E17: 46271 | G17: 46294 | H17: 2 | I17: 46286 | L17: =IF(E17="","",E17+IF(F17="",IFERROR(VLOOKUP(C17,Parametros!$E:$F,2,0),0),F17)) | M17: =IF(E17="","",IF(G17="",IF(TODAY()>L17,"Atrasada","Em aberto"),IF(G17<=L17,"No prazo","Com atraso"))) | N17: =IF(E17="","",MAX(0,IF(G17="",TODAY(),G17)-L17))
A18: PV1236 | B18: Cliente Exemplo 23 | C18: Documentação/Despachante | D18: Documentos de exportação | E18: 46271 | G18: 46280 | H18: 3 | I18: 46276 | J18: Aguardando aprovação do cliente | L18: =IF(E18="","",E18+IF(F18="",IFERROR(VLOOKUP(C18,Parametros!$E:$F,2,0),0),F18)) | M18: =IF(E18="","",IF(G18="",IF(TODAY()>L18,"Atrasada","Em aberto"),IF(G18<=L18,"No prazo","Com atraso"))) | N18: =IF(E18="","",MAX(0,IF(G18="",TODAY(),G18)-L18))
A19: PV1236 | B19: Cliente Exemplo 23 | C19: Logística/Embarque | D19: Booking e coleta do contêiner | E19: 46271 | G19: 46280 | H19: 0 | L19: =IF(E19="","",E19+IF(F19="",IFERROR(VLOOKUP(C19,Parametros!$E:$F,2,0),0),F19)) | M19: =IF(E19="","",IF(G19="",IF(TODAY()>L19,"Atrasada","Em aberto"),IF(G19<=L19,"No prazo","Com atraso"))) | N19: =IF(E19="","",MAX(0,IF(G19="",TODAY(),G19)-L19))
A20: PV1236 | B20: Cliente Exemplo 23 | C20: Qualidade/Regulatório | D20: Certificado sanitário / análise | E20: 46273 | G20: 46280 | H20: 1 | I20: 46280 | L20: =IF(E20="","",E20+IF(F20="",IFERROR(VLOOKUP(C20,Parametros!$E:$F,2,0),0),F20)) | M20: =IF(E20="","",IF(G20="",IF(TODAY()>L20,"Atrasada","Em aberto"),IF(G20<=L20,"No prazo","Com atraso"))) | N20: =IF(E20="","",MAX(0,IF(G20="",TODAY(),G20)-L20))
A21: PV1236 | B21: Cliente Exemplo 23 | C21: Comercial/Comex | D21: Proforma e confirmação | E21: 46270 | G21: 46272 | H21: 1 | I21: 46272 | L21: =IF(E21="","",E21+IF(F21="",IFERROR(VLOOKUP(C21,Parametros!$E:$F,2,0),0),F21)) | M21: =IF(E21="","",IF(G21="",IF(TODAY()>L21,"Atrasada","Em aberto"),IF(G21<=L21,"No prazo","Com atraso"))) | N21: =IF(E21="","",MAX(0,IF(G21="",TODAY(),G21)-L21))
A22: PV1235 | B22: Cliente Exemplo 23 | C22: Marketing/Arte | D22: Arte de rótulo no idioma | E22: 46278 | G22: 46287 | H22: 2 | I22: 46285 | J22: Aguardando aprovação do cliente | L22: =IF(E22="","",E22+IF(F22="",IFERROR(VLOOKUP(C22,Parametros!$E:$F,2,0),0),F22)) | M22: =IF(E22="","",IF(G22="",IF(TODAY()>L22,"Atrasada","Em aberto"),IF(G22<=L22,"No prazo","Com atraso"))) | N22: =IF(E22="","",MAX(0,IF(G22="",TODAY(),G22)-L22))
A23: PV1235 | B23: Cliente Exemplo 23 | C23: Documentação/Despachante | D23: Documentos de exportação | E23: 46280 | G23: 46293 | H23: 0 | L23: =IF(E23="","",E23+IF(F23="",IFERROR(VLOOKUP(C23,Parametros!$E:$F,2,0),0),F23)) | M23: =IF(E23="","",IF(G23="",IF(TODAY()>L23,"Atrasada","Em aberto"),IF(G23<=L23,"No prazo","Com atraso"))) | N23: =IF(E23="","",MAX(0,IF(G23="",TODAY(),G23)-L23))
A24: PV1235 | B24: Cliente Exemplo 23 | C24: Qualidade/Regulatório | D24: Certificado sanitário / análise | E24: 46281 | G24: 46285 | H24: 0 | L24: =IF(E24="","",E24+IF(F24="",IFERROR(VLOOKUP(C24,Parametros!$E:$F,2,0),0),F24)) | M24: =IF(E24="","",IF(G24="",IF(TODAY()>L24,"Atrasada","Em aberto"),IF(G24<=L24,"No prazo","Com atraso"))) | N24: =IF(E24="","",MAX(0,IF(G24="",TODAY(),G24)-L24))
A25: PV1235 | B25: Cliente Exemplo 23 | C25: Logística/Embarque | D25: Booking e coleta do contêiner | E25: 46280 | G25: 46287 | H25: 1 | I25: 46285 | J25: Aguardando aprovação do cliente | L25: =IF(E25="","",E25+IF(F25="",IFERROR(VLOOKUP(C25,Parametros!$E:$F,2,0),0),F25)) | M25: =IF(E25="","",IF(G25="",IF(TODAY()>L25,"Atrasada","Em aberto"),IF(G25<=L25,"No prazo","Com atraso"))) | N25: =IF(E25="","",MAX(0,IF(G25="",TODAY(),G25)-L25))
A26: PV1235 | B26: Cliente Exemplo 23 | C26: PCP/Produção | D26: Programar produção | E26: 46279 | G26: 46296 | H26: 1 | I26: 46294 | J26: Fornecedor atrasou | L26: =IF(E26="","",E26+IF(F26="",IFERROR(VLOOKUP(C26,Parametros!$E:$F,2,0),0),F26)) | M26: =IF(E26="","",IF(G26="",IF(TODAY()>L26,"Atrasada","Em aberto"),IF(G26<=L26,"No prazo","Com atraso"))) | N26: =IF(E26="","",MAX(0,IF(G26="",TODAY(),G26)-L26))
A27: PV1234 | B27: Cliente Exemplo 22 | C27: Documentação/Despachante | D27: Documentos de exportação | E27: 46286 | G27: 46293 | H27: 1 | I27: 46291 | L27: =IF(E27="","",E27+IF(F27="",IFERROR(VLOOKUP(C27,Parametros!$E:$F,2,0),0),F27)) | M27: =IF(E27="","",IF(G27="",IF(TODAY()>L27,"Atrasada","Em aberto"),IF(G27<=L27,"No prazo","Com atraso"))) | N27: =IF(E27="","",MAX(0,IF(G27="",TODAY(),G27)-L27))
A28: PV1234 | B28: Cliente Exemplo 22 | C28: PCP/Produção | D28: Programar produção | E28: 46287 | H28: 1 | I28: 46302 | L28: =IF(E28="","",E28+IF(F28="",IFERROR(VLOOKUP(C28,Parametros!$E:$F,2,0),0),F28)) | M28: =IF(E28="","",IF(G28="",IF(TODAY()>L28,"Atrasada","Em aberto"),IF(G28<=L28,"No prazo","Com atraso"))) | N28: =IF(E28="","",MAX(0,IF(G28="",TODAY(),G28)-L28))
A29: PV1234 | B29: Cliente Exemplo 22 | C29: Compras/Suprimentos | D29: Compra de embalagem/insumos | E29: 46287 | G29: 46299 | H29: 0 | J29: Fila da produção | L29: =IF(E29="","",E29+IF(F29="",IFERROR(VLOOKUP(C29,Parametros!$E:$F,2,0),0),F29)) | M29: =IF(E29="","",IF(G29="",IF(TODAY()>L29,"Atrasada","Em aberto"),IF(G29<=L29,"No prazo","Com atraso"))) | N29: =IF(E29="","",MAX(0,IF(G29="",TODAY(),G29)-L29))
A30: PV1234 | B30: Cliente Exemplo 22 | C30: Qualidade/Regulatório | D30: Certificado sanitário / análise | E30: 46284 | G30: 46291 | H30: 1 | I30: 46291 | L30: =IF(E30="","",E30+IF(F30="",IFERROR(VLOOKUP(C30,Parametros!$E:$F,2,0),0),F30)) | M30: =IF(E30="","",IF(G30="",IF(TODAY()>L30,"Atrasada","Em aberto"),IF(G30<=L30,"No prazo","Com atraso"))) | N30: =IF(E30="","",MAX(0,IF(G30="",TODAY(),G30)-L30))
A31: PV1234 | B31: Cliente Exemplo 22 | C31: Comercial/Comex | D31: Proforma e confirmação | E31: 46287 | G31: 46289 | H31: 0 | L31: =IF(E31="","",E31+IF(F31="",IFERROR(VLOOKUP(C31,Parametros!$E:$F,2,0),0),F31)) | M31: =IF(E31="","",IF(G31="",IF(TODAY()>L31,"Atrasada","Em aberto"),IF(G31<=L31,"No prazo","Com atraso"))) | N31: =IF(E31="","",MAX(0,IF(G31="",TODAY(),G31)-L31))
A32: PV1233 | B32: Cliente Exemplo 22 | C32: Compras/Suprimentos | D32: Compra de embalagem/insumos | E32: 46266 | G32: 46275 | H32: 1 | I32: 46276 | L32: =IF(E32="","",E32+IF(F32="",IFERROR(VLOOKUP(C32,Parametros!$E:$F,2,0),0),F32)) | M32: =IF(E32="","",IF(G32="",IF(TODAY()>L32,"Atrasada","Em aberto"),IF(G32<=L32,"No prazo","Com atraso"))) | N32: =IF(E32="","",MAX(0,IF(G32="",TODAY(),G32)-L32))
A33: PV1233 | B33: Cliente Exemplo 22 | C33: Qualidade/Regulatório | D33: Certificado sanitário / análise | E33: 46269 | G33: 46278 | H33: 1 | I33: 46276 | L33: =IF(E33="","",E33+IF(F33="",IFERROR(VLOOKUP(C33,Parametros!$E:$F,2,0),0),F33)) | M33: =IF(E33="","",IF(G33="",IF(TODAY()>L33,"Atrasada","Em aberto"),IF(G33<=L33,"No prazo","Com atraso"))) | N33: =IF(E33="","",MAX(0,IF(G33="",TODAY(),G33)-L33))
A34: PV1233 | B34: Cliente Exemplo 22 | C34: Financeiro | D34: Liberação de crédito / carta de crédito | E34: 46269 | G34: 46271 | H34: 1 | I34: 46272 | L34: =IF(E34="","",E34+IF(F34="",IFERROR(VLOOKUP(C34,Parametros!$E:$F,2,0),0),F34)) | M34: =IF(E34="","",IF(G34="",IF(TODAY()>L34,"Atrasada","Em aberto"),IF(G34<=L34,"No prazo","Com atraso"))) | N34: =IF(E34="","",MAX(0,IF(G34="",TODAY(),G34)-L34))
A35: PV1233 | B35: Cliente Exemplo 22 | C35: Marketing/Arte | D35: Arte de rótulo no idioma | E35: 46267 | G35: 46282 | H35: 0 | J35: Aguardando aprovação do cliente | L35: =IF(E35="","",E35+IF(F35="",IFERROR(VLOOKUP(C35,Parametros!$E:$F,2,0),0),F35)) | M35: =IF(E35="","",IF(G35="",IF(TODAY()>L35,"Atrasada","Em aberto"),IF(G35<=L35,"No prazo","Com atraso"))) | N35: =IF(E35="","",MAX(0,IF(G35="",TODAY(),G35)-L35))
A36: PV1233 | B36: Cliente Exemplo 22 | C36: PCP/Produção | D36: Programar produção | E36: 46269 | G36: 46288 | H36: 3 | I36: 46284 | J36: Aguardando aprovação do cliente | L36: =IF(E36="","",E36+IF(F36="",IFERROR(VLOOKUP(C36,Parametros!$E:$F,2,0),0),F36)) | M36: =IF(E36="","",IF(G36="",IF(TODAY()>L36,"Atrasada","Em aberto"),IF(G36<=L36,"No prazo","Com atraso"))) | N36: =IF(E36="","",MAX(0,IF(G36="",TODAY(),G36)-L36))
A37: PV1232 | B37: Cliente Exemplo 22 | C37: Logística/Embarque | D37: Booking e coleta do contêiner | E37: 46272 | G37: 46285 | H37: 3 | I37: 46277 | J37: Aguardando aprovação do cliente | L37: =IF(E37="","",E37+IF(F37="",IFERROR(VLOOKUP(C37,Parametros!$E:$F,2,0),0),F37)) | M37: =IF(E37="","",IF(G37="",IF(TODAY()>L37,"Atrasada","Em aberto"),IF(G37<=L37,"No prazo","Com atraso"))) | N37: =IF(E37="","",MAX(0,IF(G37="",TODAY(),G37)-L37))
A38: PV1232 | B38: Cliente Exemplo 22 | C38: Documentação/Despachante | D38: Documentos de exportação | E38: 46273 | G38: 46278 | H38: 1 | I38: 46278 | L38: =IF(E38="","",E38+IF(F38="",IFERROR(VLOOKUP(C38,Parametros!$E:$F,2,0),0),F38)) | M38: =IF(E38="","",IF(G38="",IF(TODAY()>L38,"Atrasada","Em aberto"),IF(G38<=L38,"No prazo","Com atraso"))) | N38: =IF(E38="","",MAX(0,IF(G38="",TODAY(),G38)-L38))
A39: PV1232 | B39: Cliente Exemplo 22 | C39: Financeiro | D39: Liberação de crédito / carta de crédito | E39: 46272 | G39: 46279 | H39: 2 | I39: 46275 | J39: Fila da produção | L39: =IF(E39="","",E39+IF(F39="",IFERROR(VLOOKUP(C39,Parametros!$E:$F,2,0),0),F39)) | M39: =IF(E39="","",IF(G39="",IF(TODAY()>L39,"Atrasada","Em aberto"),IF(G39<=L39,"No prazo","Com atraso"))) | N39: =IF(E39="","",MAX(0,IF(G39="",TODAY(),G39)-L39))
A40: PV1232 | B40: Cliente Exemplo 22 | C40: Qualidade/Regulatório | D40: Certificado sanitário / análise | E40: 46273 | G40: 46284 | H40: 1 | I40: 46280 | L40: =IF(E40="","",E40+IF(F40="",IFERROR(VLOOKUP(C40,Parametros!$E:$F,2,0),0),F40)) | M40: =IF(E40="","",IF(G40="",IF(TODAY()>L40,"Atrasada","Em aberto"),IF(G40<=L40,"No prazo","Com atraso"))) | N40: =IF(E40="","",MAX(0,IF(G40="",TODAY(),G40)-L40))
A41: PV1232 | B41: Cliente Exemplo 22 | C41: PCP/Produção | D41: Programar produção | E41: 46270 | G41: 46293 | H41: 1 | I41: 46285 | J41: Fila da produção | L41: =IF(E41="","",E41+IF(F41="",IFERROR(VLOOKUP(C41,Parametros!$E:$F,2,0),0),F41)) | M41: =IF(E41="","",IF(G41="",IF(TODAY()>L41,"Atrasada","Em aberto"),IF(G41<=L41,"No prazo","Com atraso"))) | N41: =IF(E41="","",MAX(0,IF(G41="",TODAY(),G41)-L41))
A42: PV1231 | B42: Cliente Exemplo 22 | C42: PCP/Produção | D42: Programar produção | E42: 46273 | G42: 46292 | H42: 1 | I42: 46288 | J42: Aguardando aprovação do cliente | L42: =IF(E42="","",E42+IF(F42="",IFERROR(VLOOKUP(C42,Parametros!$E:$F,2,0),0),F42)) | M42: =IF(E42="","",IF(G42="",IF(TODAY()>L42,"Atrasada","Em aberto"),IF(G42<=L42,"No prazo","Com atraso"))) | N42: =IF(E42="","",MAX(0,IF(G42="",TODAY(),G42)-L42))
A43: PV1231 | B43: Cliente Exemplo 22 | C43: Marketing/Arte | D43: Arte de rótulo no idioma | E43: 46275 | G43: 46290 | H43: 2 | I43: 46282 | J43: Fornecedor atrasou | L43: =IF(E43="","",E43+IF(F43="",IFERROR(VLOOKUP(C43,Parametros!$E:$F,2,0),0),F43)) | M43: =IF(E43="","",IF(G43="",IF(TODAY()>L43,"Atrasada","Em aberto"),IF(G43<=L43,"No prazo","Com atraso"))) | N43: =IF(E43="","",MAX(0,IF(G43="",TODAY(),G43)-L43))
A44: PV1231 | B44: Cliente Exemplo 22 | C44: Qualidade/Regulatório | D44: Certificado sanitário / análise | E44: 46273 | G44: 46288 | H44: 3 | I44: 46280 | J44: Fila da produção | L44: =IF(E44="","",E44+IF(F44="",IFERROR(VLOOKUP(C44,Parametros!$E:$F,2,0),0),F44)) | M44: =IF(E44="","",IF(G44="",IF(TODAY()>L44,"Atrasada","Em aberto"),IF(G44<=L44,"No prazo","Com atraso"))) | N44: =IF(E44="","",MAX(0,IF(G44="",TODAY(),G44)-L44))
A45: PV1231 | B45: Cliente Exemplo 22 | C45: Logística/Embarque | D45: Booking e coleta do contêiner | E45: 46274 | G45: 46281 | H45: 1 | I45: 46279 | J45: Fornecedor atrasou | L45: =IF(E45="","",E45+IF(F45="",IFERROR(VLOOKUP(C45,Parametros!$E:$F,2,0),0),F45)) | M45: =IF(E45="","",IF(G45="",IF(TODAY()>L45,"Atrasada","Em aberto"),IF(G45<=L45,"No prazo","Com atraso"))) | N45: =IF(E45="","",MAX(0,IF(G45="",TODAY(),G45)-L45))
A46: PV1231 | B46: Cliente Exemplo 22 | C46: Documentação/Despachante | D46: Documentos de exportação | E46: 46273 | G46: 46277 | H46: 0 | L46: =IF(E46="","",E46+IF(F46="",IFERROR(VLOOKUP(C46,Parametros!$E:$F,2,0),0),F46)) | M46: =IF(E46="","",IF(G46="",IF(TODAY()>L46,"Atrasada","Em aberto"),IF(G46<=L46,"No prazo","Com atraso"))) | N46: =IF(E46="","",MAX(0,IF(G46="",TODAY(),G46)-L46))
A47: PV1230 | B47: Cliente Exemplo 22 | C47: PCP/Produção | D47: Programar produção | E47: 46276 | G47: 46290 | H47: 2 | I47: 46291 | L47: =IF(E47="","",E47+IF(F47="",IFERROR(VLOOKUP(C47,Parametros!$E:$F,2,0),0),F47)) | M47: =IF(E47="","",IF(G47="",IF(TODAY()>L47,"Atrasada","Em aberto"),IF(G47<=L47,"No prazo","Com atraso"))) | N47: =IF(E47="","",MAX(0,IF(G47="",TODAY(),G47)-L47))
A48: PV1230 | B48: Cliente Exemplo 22 | C48: Documentação/Despachante | D48: Documentos de exportação | E48: 46277 | G48: 46290 | H48: 1 | I48: 46282 | J48: Aguardando aprovação do cliente | L48: =IF(E48="","",E48+IF(F48="",IFERROR(VLOOKUP(C48,Parametros!$E:$F,2,0),0),F48)) | M48: =IF(E48="","",IF(G48="",IF(TODAY()>L48,"Atrasada","Em aberto"),IF(G48<=L48,"No prazo","Com atraso"))) | N48: =IF(E48="","",MAX(0,IF(G48="",TODAY(),G48)-L48))
A49: PV1230 | B49: Cliente Exemplo 22 | C49: Comercial/Comex | D49: Proforma e confirmação | E49: 46278 | G49: 46288 | H49: 3 | I49: 46280 | J49: Aguardando aprovação do cliente | L49: =IF(E49="","",E49+IF(F49="",IFERROR(VLOOKUP(C49,Parametros!$E:$F,2,0),0),F49)) | M49: =IF(E49="","",IF(G49="",IF(TODAY()>L49,"Atrasada","Em aberto"),IF(G49<=L49,"No prazo","Com atraso"))) | N49: =IF(E49="","",MAX(0,IF(G49="",TODAY(),G49)-L49))
A50: PV1230 | B50: Cliente Exemplo 22 | C50: Financeiro | D50: Liberação de crédito / carta de crédito | E50: 46275 | G50: 46282 | H50: 3 | I50: 46278 | J50: Fila da produção | L50: =IF(E50="","",E50+IF(F50="",IFERROR(VLOOKUP(C50,Parametros!$E:$F,2,0),0),F50)) | M50: =IF(E50="","",IF(G50="",IF(TODAY()>L50,"Atrasada","Em aberto"),IF(G50<=L50,"No prazo","Com atraso"))) | N50: =IF(E50="","",MAX(0,IF(G50="",TODAY(),G50)-L50))
A51: PV1230 | B51: Cliente Exemplo 22 | C51: Compras/Suprimentos | D51: Compra de embalagem/insumos | E51: 46276 | G51: 46286 | H51: 1 | I51: 46286 | L51: =IF(E51="","",E51+IF(F51="",IFERROR(VLOOKUP(C51,Parametros!$E:$F,2,0),0),F51)) | M51: =IF(E51="","",IF(G51="",IF(TODAY()>L51,"Atrasada","Em aberto"),IF(G51<=L51,"No prazo","Com atraso"))) | N51: =IF(E51="","",MAX(0,IF(G51="",TODAY(),G51)-L51))
A52: PV1229 | B52: Cliente Exemplo 22 | C52: Compras/Suprimentos | D52: Compra de embalagem/insumos | E52: 46284 | G52: 46294 | H52: 1 | I52: 46294 | L52: =IF(E52="","",E52+IF(F52="",IFERROR(VLOOKUP(C52,Parametros!$E:$F,2,0),0),F52)) | M52: =IF(E52="","",IF(G52="",IF(TODAY()>L52,"Atrasada","Em aberto"),IF(G52<=L52,"No prazo","Com atraso"))) | N52: =IF(E52="","",MAX(0,IF(G52="",TODAY(),G52)-L52))
A53: PV1229 | B53: Cliente Exemplo 22 | C53: Logística/Embarque | D53: Booking e coleta do contêiner | E53: 46283 | G53: 46288 | H53: 2 | I53: 46288 | L53: =IF(E53="","",E53+IF(F53="",IFERROR(VLOOKUP(C53,Parametros!$E:$F,2,0),0),F53)) | M53: =IF(E53="","",IF(G53="",IF(TODAY()>L53,"Atrasada","Em aberto"),IF(G53<=L53,"No prazo","Com atraso"))) | N53: =IF(E53="","",MAX(0,IF(G53="",TODAY(),G53)-L53))
A54: PV1229 | B54: Cliente Exemplo 22 | C54: Qualidade/Regulatório | D54: Certificado sanitário / análise | E54: 46282 | G54: 46289 | H54: 2 | I54: 46289 | L54: =IF(E54="","",E54+IF(F54="",IFERROR(VLOOKUP(C54,Parametros!$E:$F,2,0),0),F54)) | M54: =IF(E54="","",IF(G54="",IF(TODAY()>L54,"Atrasada","Em aberto"),IF(G54<=L54,"No prazo","Com atraso"))) | N54: =IF(E54="","",MAX(0,IF(G54="",TODAY(),G54)-L54))
A55: PV1229 | B55: Cliente Exemplo 22 | C55: Comercial/Comex | D55: Proforma e confirmação | E55: 46283 | G55: 46289 | H55: 2 | I55: 46285 | J55: Aguardando aprovação do cliente | L55: =IF(E55="","",E55+IF(F55="",IFERROR(VLOOKUP(C55,Parametros!$E:$F,2,0),0),F55)) | M55: =IF(E55="","",IF(G55="",IF(TODAY()>L55,"Atrasada","Em aberto"),IF(G55<=L55,"No prazo","Com atraso"))) | N55: =IF(E55="","",MAX(0,IF(G55="",TODAY(),G55)-L55))
A56: PV1229 | B56: Cliente Exemplo 22 | C56: PCP/Produção | D56: Programar produção | E56: 46285 | G56: 46299 | H56: 3 | I56: 46300 | L56: =IF(E56="","",E56+IF(F56="",IFERROR(VLOOKUP(C56,Parametros!$E:$F,2,0),0),F56)) | M56: =IF(E56="","",IF(G56="",IF(TODAY()>L56,"Atrasada","Em aberto"),IF(G56<=L56,"No prazo","Com atraso"))) | N56: =IF(E56="","",MAX(0,IF(G56="",TODAY(),G56)-L56))
A57: PV1228 | B57: Cliente Exemplo 22 | C57: Comercial/Comex | D57: Proforma e confirmação | E57: 46287 | G57: 46297 | H57: 2 | I57: 46289 | J57: Fila da produção | L57: =IF(E57="","",E57+IF(F57="",IFERROR(VLOOKUP(C57,Parametros!$E:$F,2,0),0),F57)) | M57: =IF(E57="","",IF(G57="",IF(TODAY()>L57,"Atrasada","Em aberto"),IF(G57<=L57,"No prazo","Com atraso"))) | N57: =IF(E57="","",MAX(0,IF(G57="",TODAY(),G57)-L57))
A58: PV1228 | B58: Cliente Exemplo 22 | C58: Compras/Suprimentos | D58: Compra de embalagem/insumos | E58: 46288 | G58: 46298 | H58: 0 | L58: =IF(E58="","",E58+IF(F58="",IFERROR(VLOOKUP(C58,Parametros!$E:$F,2,0),0),F58)) | M58: =IF(E58="","",IF(G58="",IF(TODAY()>L58,"Atrasada","Em aberto"),IF(G58<=L58,"No prazo","Com atraso"))) | N58: =IF(E58="","",MAX(0,IF(G58="",TODAY(),G58)-L58))
A59: PV1228 | B59: Cliente Exemplo 22 | C59: Marketing/Arte | D59: Arte de rótulo no idioma | E59: 46286 | G59: 46297 | H59: 1 | I59: 46293 | J59: Fornecedor atrasou | L59: =IF(E59="","",E59+IF(F59="",IFERROR(VLOOKUP(C59,Parametros!$E:$F,2,0),0),F59)) | M59: =IF(E59="","",IF(G59="",IF(TODAY()>L59,"Atrasada","Em aberto"),IF(G59<=L59,"No prazo","Com atraso"))) | N59: =IF(E59="","",MAX(0,IF(G59="",TODAY(),G59)-L59))
A60: PV1228 | B60: Cliente Exemplo 22 | C60: Qualidade/Regulatório | D60: Certificado sanitário / análise | E60: 46285 | G60: 46294 | H60: 0 | J60: Fila da produção | L60: =IF(E60="","",E60+IF(F60="",IFERROR(VLOOKUP(C60,Parametros!$E:$F,2,0),0),F60)) | M60: =IF(E60="","",IF(G60="",IF(TODAY()>L60,"Atrasada","Em aberto"),IF(G60<=L60,"No prazo","Com atraso"))) | N60: =IF(E60="","",MAX(0,IF(G60="",TODAY(),G60)-L60))
A61: PV1228 | B61: Cliente Exemplo 22 | C61: PCP/Produção | D61: Programar produção | E61: 46285 | H61: 2 | I61: 46300 | L61: =IF(E61="","",E61+IF(F61="",IFERROR(VLOOKUP(C61,Parametros!$E:$F,2,0),0),F61)) | M61: =IF(E61="","",IF(G61="",IF(TODAY()>L61,"Atrasada","Em aberto"),IF(G61<=L61,"No prazo","Com atraso"))) | N61: =IF(E61="","",MAX(0,IF(G61="",TODAY(),G61)-L61))
L62: =IF(E62="","",E62+IF(F62="",IFERROR(VLOOKUP(C62,Parametros!$E:$F,2,0),0),F62)) | M62: =IF(E62="","",IF(G62="",IF(TODAY()>L62,"Atrasada","Em aberto"),IF(G62<=L62,"No prazo","Com atraso"))) | N62: =IF(E62="","",MAX(0,IF(G62="",TODAY(),G62)-L62))
L63: =IF(E63="","",E63+IF(F63="",IFERROR(VLOOKUP(C63,Parametros!$E:$F,2,0),0),F63)) | M63: =IF(E63="","",IF(G63="",IF(TODAY()>L63,"Atrasada","Em aberto"),IF(G63<=L63,"No prazo","Com atraso"))) | N63: =IF(E63="","",MAX(0,IF(G63="",TODAY(),G63)-L63))
L64: =IF(E64="","",E64+IF(F64="",IFERROR(VLOOKUP(C64,Parametros!$E:$F,2,0),0),F64)) | M64: =IF(E64="","",IF(G64="",IF(TODAY()>L64,"Atrasada","Em aberto"),IF(G64<=L64,"No prazo","Com atraso"))) | N64: =IF(E64="","",MAX(0,IF(G64="",TODAY(),G64)-L64))
L65: =IF(E65="","",E65+IF(F65="",IFERROR(VLOOKUP(C65,Parametros!$E:$F,2,0),0),F65)) | M65: =IF(E65="","",IF(G65="",IF(TODAY()>L65,"Atrasada","Em aberto"),IF(G65<=L65,"No prazo","Com atraso"))) | N65: =IF(E65="","",MAX(0,IF(G65="",TODAY(),G65)-L65))
L66: =IF(E66="","",E66+IF(F66="",IFERROR(VLOOKUP(C66,Parametros!$E:$F,2,0),0),F66)) | M66: =IF(E66="","",IF(G66="",IF(TODAY()>L66,"Atrasada","Em aberto"),IF(G66<=L66,"No prazo","Com atraso"))) | N66: =IF(E66="","",MAX(0,IF(G66="",TODAY(),G66)-L66))
L67: =IF(E67="","",E67+IF(F67="",IFERROR(VLOOKUP(C67,Parametros!$E:$F,2,0),0),F67)) | M67: =IF(E67="","",IF(G67="",IF(TODAY()>L67,"Atrasada","Em aberto"),IF(G67<=L67,"No prazo","Com atraso"))) | N67: =IF(E67="","",MAX(0,IF(G67="",TODAY(),G67)-L67))
L68: =IF(E68="","",E68+IF(F68="",IFERROR(VLOOKUP(C68,Parametros!$E:$F,2,0),0),F68)) | M68: =IF(E68="","",IF(G68="",IF(TODAY()>L68,"Atrasada","Em aberto"),IF(G68<=L68,"No prazo","Com atraso"))) | N68: =IF(E68="","",MAX(0,IF(G68="",TODAY(),G68)-L68))
L69: =IF(E69="","",E69+IF(F69="",IFERROR(VLOOKUP(C69,Parametros!$E:$F,2,0),0),F69)) | M69: =IF(E69="","",IF(G69="",IF(TODAY()>L69,"Atrasada","Em aberto"),IF(G69<=L69,"No prazo","Com atraso"))) | N69: =IF(E69="","",MAX(0,IF(G69="",TODAY(),G69)-L69))
L70: =IF(E70="","",E70+IF(F70="",IFERROR(VLOOKUP(C70,Parametros!$E:$F,2,0),0),F70)) | M70: =IF(E70="","",IF(G70="",IF(TODAY()>L70,"Atrasada","Em aberto"),IF(G70<=L70,"No prazo","Com atraso"))) | N70: =IF(E70="","",MAX(0,IF(G70="",TODAY(),G70)-L70))
L71: =IF(E71="","",E71+IF(F71="",IFERROR(VLOOKUP(C71,Parametros!$E:$F,2,0),0),F71)) | M71: =IF(E71="","",IF(G71="",IF(TODAY()>L71,"Atrasada","Em aberto"),IF(G71<=L71,"No prazo","Com atraso"))) | N71: =IF(E71="","",MAX(0,IF(G71="",TODAY(),G71)-L71))
L72: =IF(E72="","",E72+IF(F72="",IFERROR(VLOOKUP(C72,Parametros!$E:$F,2,0),0),F72)) | M72: =IF(E72="","",IF(G72="",IF(TODAY()>L72,"Atrasada","Em aberto"),IF(G72<=L72,"No prazo","Com atraso"))) | N72: =IF(E72="","",MAX(0,IF(G72="",TODAY(),G72)-L72))
L73: =IF(E73="","",E73+IF(F73="",IFERROR(VLOOKUP(C73,Parametros!$E:$F,2,0),0),F73)) | M73: =IF(E73="","",IF(G73="",IF(TODAY()>L73,"Atrasada","Em aberto"),IF(G73<=L73,"No prazo","Com atraso"))) | N73: =IF(E73="","",MAX(0,IF(G73="",TODAY(),G73)-L73))
... L2001: =IF(E2001="","",E2001+IF(F2001="",IFERROR(VLOOKUP(C2001,Parametros!$E:$F,2,0),0),F2001)) | M2001: =IF(E2001="","",IF(G2001="",IF(TODAY()>L2001,"Atrasada","Em aberto"),IF(G2001<=L2001,"No prazo","Com atraso"))) | N2001: =IF(E2001="","",MAX(0,IF(G2001="",TODAY(),G2001)-L2001))

Sheet Custos
A1: Mês ref. | B1: Categoria | C1: Descrição da ação | D1: Tipo de ganho | E1: Custo de referência (R$) | F1: Custo realizado (R$) | G1: Evidência | H1: Responsável | I1: Economia (R$)
A2: 46266 | B2: Amostras | C2: Cliente C004 pagou o courier das amostras (antes por nossa conta) | D2: Custo transferido ao cliente | E2: 850 | F2: 0 | G2: E-mail 12/09 | H2: Gerente Comex | I2: =IF(AND(E2="",F2=""),"",E2-F2)
A3: 46266 | B3: Inspeções | C3: Inspeção de dois pedidos (C002 e C009) feita na mesma visita | D3: Custo evitado | E3: 3200 | F3: 1600 | G3: Agenda da certificadora | H3: Gerente Comex | I3: =IF(AND(E3="",F3=""),"",E3-F3)
A4: 46266 | B4: Impressões / documentos | C4: Documentos de embarque enviados só em PDF | D4: Economia direta | E4: 420 | F4: 90 | G4: Controle de impressões | H4: Gerente Comex | I4: =IF(AND(E4="",F4=""),"",E4-F4)
A5: 46266 | B5: Viagens internacionais | C5: Visita ao cliente C011 substituída por reunião on-line | D5: Custo evitado | E5: 14500 | F5: 0 | G5: Orçamento da agência | H5: Gerente Comex | I5: =IF(AND(E5="",F5=""),"",E5-F5)
I6: =IF(AND(E6="",F6=""),"",E6-F6)
I7: =IF(AND(E7="",F7=""),"",E7-F7)
I8: =IF(AND(E8="",F8=""),"",E8-F8)
I9: =IF(AND(E9="",F9=""),"",E9-F9)
I10: =IF(AND(E10="",F10=""),"",E10-F10)
I11: =IF(AND(E11="",F11=""),"",E11-F11)
I12: =IF(AND(E12="",F12=""),"",E12-F12)
I13: =IF(AND(E13="",F13=""),"",E13-F13)
I14: =IF(AND(E14="",F14=""),"",E14-F14)
I15: =IF(AND(E15="",F15=""),"",E15-F15)
I16: =IF(AND(E16="",F16=""),"",E16-F16)
I17: =IF(AND(E17="",F17=""),"",E17-F17)
... I301: =IF(AND(E301="",F301=""),"",E301-F301)

Sheet Embalagens
A1: Código | B1: Descrição | C1: Tipo | D1: Produto/linha | E1: Idioma | F1: Mercado original | G1: Medidas (cm) | H1: Qtd em estoque | I1: Unidade | J1: Custo unit. (R$) | K1: Data de entrada | L1: Status | M1: Localização | N1: Observação | O1: Valor em estoque (R$) | P1: Idade (meses) | Q1: Qtd já utilizada
A2: EMB-101 | B2: Caixa master Produto A - espanhol (layout 2021) | C2: Caixa master | D2: Produto A | E2: Espanhol | F2: Paraguai | G2: 40x30x25 | H2: 3200 | I2: un | J2: 3.8 | K2: 44326 | L2: Obsoleta | M2: Galpão 2 | O2: =IF(A2="","",H2*J2) | P2: =IF(K2="","",DATEDIF(K2,TODAY(),"m")) | Q2: =IF(A2="","",SUMIFS(Uso_Embalagens!$E:$E,Uso_Embalagens!$D:$D,A2))
A3: EMB-102 | B3: Cartucho Produto A - inglês (EUA, 2020) | C3: Cartucho | D3: Produto A | E3: Inglês | F3: Estados Unidos | G3: 15x10x5 | H3: 18000 | I3: un | J3: 0.65 | K3: 44138 | L3: Obsoleta | M3: Galpão 2 | N3: Tabela nutricional antiga | O3: =IF(A3="","",H3*J3) | P3: =IF(K3="","",DATEDIF(K3,TODAY(),"m")) | Q3: =IF(A3="","",SUMIFS(Uso_Embalagens!$E:$E,Uso_Embalagens!$D:$D,A3))
A4: EMB-103 | B4: Caixa master Produto B - árabe/inglês | C4: Caixa master | D4: Produto B | E4: Inglês/Árabe | F4: Emirados Árabes | G4: 50x35x30 | H4: 1500 | I4: un | J4: 5.2 | K4: 44606 | L4: Obsoleta | M4: Galpão 1 | O4: =IF(A4="","",H4*J4) | P4: =IF(K4="","",DATEDIF(K4,TODAY(),"m")) | Q4: =IF(A4="","",SUMIFS(Uso_Embalagens!$E:$E,Uso_Embalagens!$D:$D,A4))
A5: EMB-104 | B5: Caixa master neutra sem impressão | C5: Caixa master | D5: Geral | E5: Neutra | G5: 40x30x25 | H5: 900 | I5: un | J5: 3.1 | K5: 45108 | L5: Ativa | M5: Galpão 1 | O5: =IF(A5="","",H5*J5) | P5: =IF(K5="","",DATEDIF(K5,TODAY(),"m")) | Q5: =IF(A5="","",SUMIFS(Uso_Embalagens!$E:$E,Uso_Embalagens!$D:$D,A5))
A6: EMB-105 | B6: Saco 25kg - japonês | C6: Saco/filme | D6: Produto C | E6: Japonês | F6: Japão | H6: 2400 | I6: un | J6: 2.1 | K6: 44459 | L6: Obsoleta | M6: Galpão 3 | O6: =IF(A6="","",H6*J6) | P6: =IF(K6="","",DATEDIF(K6,TODAY(),"m")) | Q6: =IF(A6="","",SUMIFS(Uso_Embalagens!$E:$E,Uso_Embalagens!$D:$D,A6))
A7: EMB-106 | B7: Divisória papelão ondulado | C7: Divisória/reforço | D7: Geral | E7: Neutra | G7: 38x28 | H7: 6000 | I7: un | J7: 0.4 | K7: 44655 | L7: Obsoleta | M7: Galpão 3 | O7: =IF(A7="","",H7*J7) | P7: =IF(K7="","",DATEDIF(K7,TODAY(),"m")) | Q7: =IF(A7="","",SUMIFS(Uso_Embalagens!$E:$E,Uso_Embalagens!$D:$D,A7))
A8: EMB-107 | B8: Caixa master Produto B - português (Angola 2019) | C8: Caixa master | D8: Produto B | E8: Português | F8: Angola | G8: 50x35x30 | H8: 2100 | I8: un | J8: 5 | K8: 43707 | L8: Obsoleta | M8: Galpão 2 | N8: Logo antigo | O8: =IF(A8="","",H8*J8) | P8: =IF(K8="","",DATEDIF(K8,TODAY(),"m")) | Q8: =IF(A8="","",SUMIFS(Uso_Embalagens!$E:$E,Uso_Embalagens!$D:$D,A8))
O9: =IF(A9="","",H9*J9) | P9: =IF(K9="","",DATEDIF(K9,TODAY(),"m")) | Q9: =IF(A9="","",SUMIFS(Uso_Embalagens!$E:$E,Uso_Embalagens!$D:$D,A9))
O10: =IF(A10="","",H10*J10) | P10: =IF(K10="","",DATEDIF(K10,TODAY(),"m")) | Q10: =IF(A10="","",SUMIFS(Uso_Embalagens!$E:$E,Uso_Embalagens!$D:$D,A10))
O11: =IF(A11="","",H11*J11) | P11: =IF(K11="","",DATEDIF(K11,TODAY(),"m")) | Q11: =IF(A11="","",SUMIFS(Uso_Embalagens!$E:$E,Uso_Embalagens!$D:$D,A11))
O12: =IF(A12="","",H12*J12) | P12: =IF(K12="","",DATEDIF(K12,TODAY(),"m")) | Q12: =IF(A12="","",SUMIFS(Uso_Embalagens!$E:$E,Uso_Embalagens!$D:$D,A12))
O13: =IF(A13="","",H13*J13) | P13: =IF(K13="","",DATEDIF(K13,TODAY(),"m")) | Q13: =IF(A13="","",SUMIFS(Uso_Embalagens!$E:$E,Uso_Embalagens!$D:$D,A13))
O14: =IF(A14="","",H14*J14) | P14: =IF(K14="","",DATEDIF(K14,TODAY(),"m")) | Q14: =IF(A14="","",SUMIFS(Uso_Embalagens!$E:$E,Uso_Embalagens!$D:$D,A14))
O15: =IF(A15="","",H15*J15) | P15: =IF(K15="","",DATEDIF(K15,TODAY(),"m")) | Q15: =IF(A15="","",SUMIFS(Uso_Embalagens!$E:$E,Uso_Embalagens!$D:$D,A15))
O16: =IF(A16="","",H16*J16) | P16: =IF(K16="","",DATEDIF(K16,TODAY(),"m")) | Q16: =IF(A16="","",SUMIFS(Uso_Embalagens!$E:$E,Uso_Embalagens!$D:$D,A16))
O17: =IF(A17="","",H17*J17) | P17: =IF(K17="","",DATEDIF(K17,TODAY(),"m")) | Q17: =IF(A17="","",SUMIFS(Uso_Embalagens!$E:$E,Uso_Embalagens!$D:$D,A17))
O18: =IF(A18="","",H18*J18) | P18: =IF(K18="","",DATEDIF(K18,TODAY(),"m")) | Q18: =IF(A18="","",SUMIFS(Uso_Embalagens!$E:$E,Uso_Embalagens!$D:$D,A18))
O19: =IF(A19="","",H19*J19) | P19: =IF(K19="","",DATEDIF(K19,TODAY(),"m")) | Q19: =IF(A19="","",SUMIFS(Uso_Embalagens!$E:$E,Uso_Embalagens!$D:$D,A19))
O20: =IF(A20="","",H20*J20) | P20: =IF(K20="","",DATEDIF(K20,TODAY(),"m")) | Q20: =IF(A20="","",SUMIFS(Uso_Embalagens!$E:$E,Uso_Embalagens!$D:$D,A20))
... O501: =IF(A501="","",H501*J501) | P501: =IF(K501="","",DATEDIF(K501,TODAY(),"m")) | Q501: =IF(A501="","",SUMIFS(Uso_Embalagens!$E:$E,Uso_Embalagens!$D:$D,A501))

Sheet Uso_Embalagens
A1: Data | B1: Nº Pedido | C1: Cliente | D1: Código embalagem | E1: Qtd utilizada | F1: Forma de uso | G1: Aprovado pela produção | H1: Observação | I1: Descrição | J1: Economia (R$)
A2: 46280 | B2: PV1236 | D2: EMB-106 | E2: 400 | F2: Reforço/acessório | G2: Sim | H2: Divisória entre camadas | I2: =IF(D2="","",IFERROR(INDEX(Embalagens!$B:$B,MATCH(D2,Embalagens!$A:$A,0)),"Código não cadastrado")) | J2: =IF(D2="","",E2*IFERROR(INDEX(Embalagens!$J:$J,MATCH(D2,Embalagens!$A:$A,0)),0))
I3: =IF(D3="","",IFERROR(INDEX(Embalagens!$B:$B,MATCH(D3,Embalagens!$A:$A,0)),"Código não cadastrado")) | J3: =IF(D3="","",E3*IFERROR(INDEX(Embalagens!$J:$J,MATCH(D3,Embalagens!$A:$A,0)),0))
I4: =IF(D4="","",IFERROR(INDEX(Embalagens!$B:$B,MATCH(D4,Embalagens!$A:$A,0)),"Código não cadastrado")) | J4: =IF(D4="","",E4*IFERROR(INDEX(Embalagens!$J:$J,MATCH(D4,Embalagens!$A:$A,0)),0))
I5: =IF(D5="","",IFERROR(INDEX(Embalagens!$B:$B,MATCH(D5,Embalagens!$A:$A,0)),"Código não cadastrado")) | J5: =IF(D5="","",E5*IFERROR(INDEX(Embalagens!$J:$J,MATCH(D5,Embalagens!$A:$A,0)),0))
I6: =IF(D6="","",IFERROR(INDEX(Embalagens!$B:$B,MATCH(D6,Embalagens!$A:$A,0)),"Código não cadastrado")) | J6: =IF(D6="","",E6*IFERROR(INDEX(Embalagens!$J:$J,MATCH(D6,Embalagens!$A:$A,0)),0))
I7: =IF(D7="","",IFERROR(INDEX(Embalagens!$B:$B,MATCH(D7,Embalagens!$A:$A,0)),"Código não cadastrado")) | J7: =IF(D7="","",E7*IFERROR(INDEX(Embalagens!$J:$J,MATCH(D7,Embalagens!$A:$A,0)),0))
I8: =IF(D8="","",IFERROR(INDEX(Embalagens!$B:$B,MATCH(D8,Embalagens!$A:$A,0)),"Código não cadastrado")) | J8: =IF(D8="","",E8*IFERROR(INDEX(Embalagens!$J:$J,MATCH(D8,Embalagens!$A:$A,0)),0))
I9: =IF(D9="","",IFERROR(INDEX(Embalagens!$B:$B,MATCH(D9,Embalagens!$A:$A,0)),"Código não cadastrado")) | J9: =IF(D9="","",E9*IFERROR(INDEX(Embalagens!$J:$J,MATCH(D9,Embalagens!$A:$A,0)),0))
I10: =IF(D10="","",IFERROR(INDEX(Embalagens!$B:$B,MATCH(D10,Embalagens!$A:$A,0)),"Código não cadastrado")) | J10: =IF(D10="","",E10*IFERROR(INDEX(Embalagens!$J:$J,MATCH(D10,Embalagens!$A:$A,0)),0))
I11: =IF(D11="","",IFERROR(INDEX(Embalagens!$B:$B,MATCH(D11,Embalagens!$A:$A,0)),"Código não cadastrado")) | J11: =IF(D11="","",E11*IFERROR(INDEX(Embalagens!$J:$J,MATCH(D11,Embalagens!$A:$A,0)),0))
I12: =IF(D12="","",IFERROR(INDEX(Embalagens!$B:$B,MATCH(D12,Embalagens!$A:$A,0)),"Código não cadastrado")) | J12: =IF(D12="","",E12*IFERROR(INDEX(Embalagens!$J:$J,MATCH(D12,Embalagens!$A:$A,0)),0))
I13: =IF(D13="","",IFERROR(INDEX(Embalagens!$B:$B,MATCH(D13,Embalagens!$A:$A,0)),"Código não cadastrado")) | J13: =IF(D13="","",E13*IFERROR(INDEX(Embalagens!$J:$J,MATCH(D13,Embalagens!$A:$A,0)),0))
I14: =IF(D14="","",IFERROR(INDEX(Embalagens!$B:$B,MATCH(D14,Embalagens!$A:$A,0)),"Código não cadastrado")) | J14: =IF(D14="","",E14*IFERROR(INDEX(Embalagens!$J:$J,MATCH(D14,Embalagens!$A:$A,0)),0))
... I1001: =IF(D1001="","",IFERROR(INDEX(Embalagens!$B:$B,MATCH(D1001,Embalagens!$A:$A,0)),"Código não cadastrado")) | J1001: =IF(D1001="","",E1001*IFERROR(INDEX(Embalagens!$J:$J,MATCH(D1001,Embalagens!$A:$A,0)),0))

Sheet Listas
A1: Status cadastro | B1: Periodicidade | C1: Situação | D1: Motivo | E1: Status da ação | F1: Chance de recompra | G1: Departamento | H1: Categoria custo | I1: Tipo de ganho | J1: Tipo embalagem | K1: Status embalagem | L1: Forma de uso | M1: Sim/Não
A2: Ativo | B2: 1 | C2: Não recomprou | D2: Estoque alto no cliente | E2: Aberta | F2: Alta | G2: Comercial/Comex | H2: Amostras | I2: Economia direta | J2: Caixa master | K2: Obsoleta | L2: Mesmo idioma | M2: Sim
A3: Inativo | B3: 2 | C3: Atrasado | D3: Preço / câmbio | E3: Concluída | F3: Média | G3: Compras/Suprimentos | H3: Frete de amostras | I3: Custo evitado | J3: Cartucho | K3: Ativa | L3: Bonificação | M3: Não
A4: Perdido | B4: 3 | C4: Recomprou | D4: Perdeu para concorrente | E4: Cancelada | F4: Baixa | G4: Marketing/Arte | H4: Inspeções | I4: Custo transferido ao cliente | J4: Saco/filme | K4: Em avaliação | L4: Reforço/acessório
A5: Prospect | B5: 4 | C5: Novo/reativado | D5: Reclamação de qualidade | G5: Qualidade/Regulatório | H5: Viagens internacionais | I5: Receita recuperada | J5: Etiqueta | L5: Reetiquetagem/neutra
B6: 6 | C6: Antecipou | D6: Atraso em embarque anterior | G6: PCP/Produção | H6: Impressões / documentos | J6: Bandeja | L6: Descarte/reciclagem
B7: 12 | C7: Perdido | D7: Barreira sanitária / regulatória | G7: Logística/Embarque | H7: Courier | J7: Divisória/reforço
D8: Frete / contêiner / logística | G8: Financeiro | H8: Frete internacional | J8: Outro
D9: Demanda sazonal | G9: Documentação/Despachante | H9: Embalagens reaproveitadas
D10: Crédito / financeiro do cliente | H10: Certificados / taxas
D11: Troca de comprador / estrutura | H11: Outros
D12: Produto indisponível
D13: Pedido adiado para o mês seguinte
D14: Cliente encerrou atividade
D15: Sem retorno do cliente
D16: Outro
